<?xml version="1.0" encoding="UTF-8"?>
<list xmlns:xsi="http://www.w3.org/2001/XMLSchema-instance" xsi:noNamespaceSchemaLocation="../../xsd/skillTrees.xsd">
	<!-- Iss Hierophant -->
	<skillTree type="classSkillTree" classId="171" parentClassId="98">
		<skill skillName="Crystallize" skillId="248" skillLevel="1" getLevel="85" autoGet="true" />
		<skill skillName="Crystallize" skillId="248" skillLevel="2" getLevel="85" autoGet="true" />
		<skill skillName="Crystallize" skillId="248" skillLevel="3" getLevel="85" autoGet="true" />
		<skill skillName="Crystallize" skillId="248" skillLevel="4" getLevel="85" autoGet="true" />
		<skill skillName="Crystallize" skillId="248" skillLevel="5" getLevel="85" autoGet="true" />
		<skill skillName="Crystallize" skillId="248" skillLevel="6" getLevel="85" autoGet="true" />
		<skill skillName="Crippling Attack" skillId="11509" skillLevel="1" getLevel="85" levelUpSp="10000">
			<removeSkill id="1564" /> <!-- Penetrating Attack -->
		</skill>
		<skill skillName="Assault Rush" skillId="11508" skillLevel="1" getLevel="85" levelUpSp="10000" />
		<skill skillName="Quick Return" skillId="11563" skillLevel="1" getLevel="85" levelUpSp="10000">
			<removeSkill id="1050" /> <!-- Return -->
		</skill>
		<skill skillName="Superior Anti Magic" skillId="11505" skillLevel="1" getLevel="85" levelUpSp="10000">
			<removeSkill id="146" /> <!-- Anti Magic -->
		</skill>
		<skill skillName="Superior Quick Recovery" skillId="11548" skillLevel="1" getLevel="85" levelUpSp="10000">
			<removeSkill id="164" /> <!-- Quick Recovery -->
		</skill>
		<skill skillName="Superior Focus Mind" skillId="11553" skillLevel="1" getLevel="85" levelUpSp="10000" />
		<skill skillName="Superior Divine Lore" skillId="11552" skillLevel="1" getLevel="85" levelUpSp="10000">
			<removeSkill id="436" /> <!-- Divine Lore -->
		</skill>
		<skill skillName="Superior Fast Spell Casting" skillId="11555" skillLevel="1" getLevel="85" levelUpSp="10000">
			<removeSkill id="228" /> <!-- Fast Spell Casting -->
		</skill>
		<skill skillName="Superior Light Armor Mastery" skillId="11503" skillLevel="1" getLevel="85" levelUpSp="10000">
			<removeSkill id="229" /> <!-- Fast Mana Recovery -->
		</skill>
		<skill skillName="Superior Robe Mastery" skillId="11502" skillLevel="1" getLevel="85" levelUpSp="10000">
			<removeSkill id="229" /> <!-- Fast Mana Recovery -->
		</skill>
		<skill skillName="Superior Sword/Blunt Weapon Mastery" skillId="11526" skillLevel="1" getLevel="85" levelUpSp="10000">
			<removeSkill id="331" /> <!-- Skill Mastery -->
			<removeSkill id="935" /> <!-- Sigil Mastery -->
			<removeSkill id="249" /> <!-- Weapon Mastery -->
		</skill>
		<skill skillName="Superior Dual Weapon Mastery" skillId="11501" skillLevel="1" getLevel="85" levelUpSp="10000">
			<removeSkill id="331" /> <!-- Skill Mastery -->
			<removeSkill id="935" /> <!-- Sigil Mastery -->
			<removeSkill id="249" /> <!-- Weapon Mastery -->
		</skill>
		<skill skillName="Superior Heavy Armor Mastery" skillId="11504" skillLevel="1" getLevel="85" levelUpSp="10000">
			<removeSkill id="229" /> <!-- Fast Mana Recovery -->
		</skill>
		<skill skillName="Superior Mana Steal" skillId="11549" skillLevel="1" getLevel="85" levelUpSp="10000" />
		<skill skillName="Superior HP Recovery" skillId="11547" skillLevel="1" getLevel="85" levelUpSp="10000">
			<removeSkill id="212" /> <!-- Fast HP Recovery -->
		</skill>
		<skill skillName="Superior Advantage" skillId="11581" skillLevel="1" getLevel="85" levelUpSp="10000" />
		<skill skillName="Superior Mental Attack Resistance" skillId="11551" skillLevel="1" getLevel="85" levelUpSp="10000">
			<removeSkill id="328" /> <!-- Wisdom -->
			<removeSkill id="329" /> <!-- Health -->
		</skill>
		<skill skillName="Superior MP Boost" skillId="11507" skillLevel="1" getLevel="85" levelUpSp="10000">
			<removeSkill id="213" /> <!-- Boost Mana -->
		</skill>
		<skill skillName="Superior HP Boost" skillId="11506" skillLevel="1" getLevel="85" levelUpSp="10000">
			<removeSkill id="211" /> <!-- Boost HP -->
		</skill>
		<skill skillName="Superior Sixth Sense" skillId="11554" skillLevel="1" getLevel="85" levelUpSp="10000" />
		<skill skillName="Angel's Resurrection" skillId="11564" skillLevel="1" getLevel="85" levelUpSp="10000" />
		<skill skillName="Divine Cancel" skillId="11536" skillLevel="1" getLevel="85" levelUpSp="10000" />
		<skill skillName="Warrior's Harmony" skillId="11524" skillLevel="1" getLevel="85" levelUpSp="10000">
			<removeSkill id="1062" /> <!-- Berserker Spirit -->
			<removeSkill id="1388" /> <!-- Greater Might -->
		</skill>
		<skill skillName="Wizard's Harmony" skillId="11525" skillLevel="1" getLevel="85" levelUpSp="10000">
			<removeSkill id="336" /> <!-- Arcane Wisdom -->
			<removeSkill id="1078" /> <!-- Concentration -->
		</skill>
		<skill skillName="Knight's Harmony" skillId="11523" skillLevel="1" getLevel="85" levelUpSp="10000">
			<removeSkill id="1243" /> <!-- Blessed Shield -->
			<removeSkill id="1389" /> <!-- Greater Shield -->
		</skill>
		<skill skillName="Giant Root" skillId="11561" skillLevel="1" getLevel="85" levelUpSp="10000">
			<removeSkill id="1201" /> <!-- Dryad Root -->
		</skill>
		<skill skillName="Devil's Movement" skillId="11562" skillLevel="1" getLevel="85" levelUpSp="10000" />
		<skill skillName="Transform" skillId="11537" skillLevel="1" getLevel="85" levelUpSp="10000">
			<removeSkill id="1395" /> <!-- Erase -->
		</skill>
		<skill skillName="Weight Limit" skillId="150" skillLevel="3" getLevel="85" autoGet="true" />
		<skill skillName="Mass Transform" skillId="11580" skillLevel="1" getLevel="85" levelUpSp="10000" />
		<skill skillName="Mass Giant Root" skillId="11538" skillLevel="1" getLevel="85" levelUpSp="10000">
			<removeSkill id="1272" /> <!-- Word of Fear -->
		</skill>
		<skill skillName="Shadow Blade" skillId="11510" skillLevel="1" getLevel="85" levelUpSp="10000" />
		<skill skillName="Quick Escape" skillId="11540" skillLevel="1" getLevel="85" levelUpSp="10000" />
		<skill skillName="Celestial Aegis" skillId="11560" skillLevel="1" getLevel="85" levelUpSp="10000" />
		<skill skillName="Polymorph" skillId="11541" skillLevel="1" getLevel="85" levelUpSp="10000" />
		<skill skillName="Ultimate Oblivion" skillId="11558" skillLevel="1" getLevel="85" levelUpSp="10000">
			<removeSkill id="1412" /> <!-- Spell Turning -->
		</skill>
		<skill skillName="Ultimate Scourge" skillId="11557" skillLevel="1" getLevel="85" levelUpSp="10000">
			<removeSkill id="1358" /> <!-- Block Shield -->
		</skill>
		<skill skillName="Harp Melody" skillId="11521" skillLevel="1" getLevel="85" levelUpSp="10000">
			<removeSkill id="1240" /> <!-- Guidance -->
		</skill>
		<skill skillName="Drum Melody" skillId="11518" skillLevel="1" getLevel="85" levelUpSp="10000">
			<removeSkill id="1356" /> <!-- Prophecy of Fire -->
		</skill>
		<skill skillName="Recovery Melody" skillId="11571" skillLevel="1" getLevel="85" levelUpSp="10000" />
		<skill skillName="Guitar Melody" skillId="11520" skillLevel="1" getLevel="85" levelUpSp="10000">
			<removeSkill id="1077" /> <!-- Focus -->
			<removeSkill id="1242" /> <!-- Death Whisper -->
		</skill>
		<skill skillName="Lute Melody" skillId="11522" skillLevel="1" getLevel="85" levelUpSp="10000">
			<removeSkill id="1085" /> <!-- Acumen -->
			<removeSkill id="1086" /> <!-- Haste -->
		</skill>
		<skill skillName="Pipe Organ Melody" skillId="11519" skillLevel="1" getLevel="85" levelUpSp="10000">
			<removeSkill id="1044" /> <!-- Regeneration -->
			<removeSkill id="1045" /> <!-- Blessed Body -->
			<removeSkill id="1048" /> <!-- Blessed Soul -->
		</skill>
		<skill skillName="Horn Melody" skillId="11517" skillLevel="1" getLevel="85" levelUpSp="10000">
			<removeSkill id="1068" /> <!-- Might -->
			<removeSkill id="1040" /> <!-- Shield -->
			<removeSkill id="1036" /> <!-- Magic Barrier -->
		</skill>
		<skill skillName="Healing Melody" skillId="11570" skillLevel="1" getLevel="85" levelUpSp="10000" />
		<skill skillName="Petrify" skillId="11539" skillLevel="1" getLevel="85" levelUpSp="10000" />
		<skill skillName="Mass Crippling Attack" skillId="11513" skillLevel="1" getLevel="85" levelUpSp="10000" />
		<skill skillName="Ultimate Suspension" skillId="11559" skillLevel="1" getLevel="85" levelUpSp="10000">
			<removeSkill id="1359" /> <!-- Block Wind Walk -->
		</skill>
		<skill skillName="Create Common Item" skillId="1320" skillLevel="10" getLevel="85" autoGet="true" />
		<skill skillName="Mass Shadow Blade" skillId="11514" skillLevel="1" getLevel="85" levelUpSp="10000" />
		<skill skillName="Prevailing Sonata" skillId="11529" skillLevel="1" getLevel="85" levelUpSp="10000" />
		<skill skillName="Daring Sonata" skillId="11530" skillLevel="1" getLevel="85" levelUpSp="10000" />
		<skill skillName="Refreshing Sonata" skillId="11532" skillLevel="1" getLevel="85" levelUpSp="10000">
			<removeSkill id="1073" /> <!-- Eva's Kiss -->
		</skill>
		<skill skillName="Holy Attack Resistance" skillId="11566" skillLevel="1" getLevel="85" levelUpSp="10000">
			<removeSkill id="1032" /> <!-- Invigor -->
			<removeSkill id="1033" /> <!-- Poison Resistance -->
			<removeSkill id="1392" /> <!-- Holy Attack Resistance -->
			<removeSkill id="1393" /> <!-- Dark Attack Resistance -->
		</skill>
		<skill skillName="Mental Attack Resistance" skillId="11567" skillLevel="1" getLevel="85" levelUpSp="10000">
			<removeSkill id="1035" /> <!-- Mental Shield -->
		</skill>
		<skill skillName="Elemental Resistance" skillId="11565" skillLevel="1" getLevel="85" levelUpSp="10000">
			<removeSkill id="1191" /> <!-- Fire Resistance -->
			<removeSkill id="1182" /> <!-- Water Resistance -->
			<removeSkill id="1189" /> <!-- Wind Resistance -->
			<removeSkill id="1548" /> <!-- Earth Resistance -->
			<removeSkill id="1352" /> <!-- Elemental Resistance -->
		</skill>
		<skill skillName="Death Strike" skillId="11511" skillLevel="1" getLevel="85" levelUpSp="10000" />
		<skill skillName="Crippling Attack" skillId="11509" skillLevel="2" getLevel="86" levelUpSp="50000" />
		<skill skillName="Divine Cancel" skillId="11536" skillLevel="2" getLevel="86" levelUpSp="50000" />
		<skill skillName="Transform" skillId="11537" skillLevel="2" getLevel="86" levelUpSp="50000" />
		<skill skillName="Mass Crippling Attack" skillId="11513" skillLevel="2" getLevel="86" levelUpSp="50000" />
		<skill skillName="Death Strike" skillId="11511" skillLevel="2" getLevel="86" levelUpSp="50000" />
		<skill skillName="Assault Rush" skillId="11508" skillLevel="2" getLevel="87" levelUpSp="60000" />
		<skill skillName="Shadow Blade" skillId="11510" skillLevel="2" getLevel="87" levelUpSp="60000" />
		<skill skillName="Petrify" skillId="11539" skillLevel="2" getLevel="87" levelUpSp="60000" />
		<skill skillName="Angel's Touch" skillId="11534" skillLevel="1" getLevel="87" levelUpSp="60000" />
		<skill skillName="Mass Shadow Blade" skillId="11514" skillLevel="2" getLevel="87" levelUpSp="60000" />
		<skill skillName="Crippling Attack" skillId="11509" skillLevel="3" getLevel="88" levelUpSp="80000" />
		<skill skillName="Transform" skillId="11537" skillLevel="3" getLevel="88" levelUpSp="80000" />
		<skill skillName="Mass Crippling Attack" skillId="11513" skillLevel="3" getLevel="88" levelUpSp="80000" />
		<skill skillName="Death Strike" skillId="11511" skillLevel="3" getLevel="88" levelUpSp="80000" />
		<skill skillName="Divine Cancel" skillId="11536" skillLevel="3" getLevel="89" levelUpSp="100000" />
		<skill skillName="Shadow Blade" skillId="11510" skillLevel="3" getLevel="89" levelUpSp="100000" />
		<skill skillName="Petrify" skillId="11539" skillLevel="3" getLevel="89" levelUpSp="100000" />
		<skill skillName="Battle Rhapsody" skillId="11544" skillLevel="1" getLevel="89" levelUpSp="100000">
			<removeSkill id="1411" /> <!-- Mystic Immunity -->
		</skill>
		<skill skillName="Mass Shadow Blade" skillId="11514" skillLevel="3" getLevel="89" levelUpSp="100000" />
		<skill skillName="Crippling Attack" skillId="11509" skillLevel="4" getLevel="90" levelUpSp="370000" />
		<skill skillName="Assault Rush" skillId="11508" skillLevel="3" getLevel="90" levelUpSp="370000" />
		<skill skillName="Superior Divine Lore" skillId="11552" skillLevel="2" getLevel="90" levelUpSp="370000" />
		<skill skillName="Superior Advantage" skillId="11581" skillLevel="2" getLevel="90" levelUpSp="370000" />
		<skill skillName="Angel's Resurrection" skillId="11564" skillLevel="2" getLevel="90" levelUpSp="370000" />
		<skill skillName="Giant Root" skillId="11561" skillLevel="2" getLevel="90" levelUpSp="370000" />
		<skill skillName="Mass Transform" skillId="11580" skillLevel="2" getLevel="90" levelUpSp="370000" />
		<skill skillName="Mass Giant Root" skillId="11538" skillLevel="2" getLevel="90" levelUpSp="370000" />
		<skill skillName="Quick Escape" skillId="11540" skillLevel="2" getLevel="90" levelUpSp="370000" />
		<skill skillName="Harp Melody" skillId="11521" skillLevel="2" getLevel="90" levelUpSp="370000" />
		<skill skillName="Drum Melody" skillId="11518" skillLevel="2" getLevel="90" levelUpSp="370000" />
		<skill skillName="Guitar Melody" skillId="11520" skillLevel="2" getLevel="90" levelUpSp="370000" />
		<skill skillName="Lute Melody" skillId="11522" skillLevel="2" getLevel="90" levelUpSp="370000" />
		<skill skillName="Pipe Organ Melody" skillId="11519" skillLevel="2" getLevel="90" levelUpSp="370000" />
		<skill skillName="Horn Melody" skillId="11517" skillLevel="2" getLevel="90" levelUpSp="370000" />
		<skill skillName="Mass Crippling Attack" skillId="11513" skillLevel="4" getLevel="90" levelUpSp="370000" />
		<skill skillName="Angel's Touch" skillId="11534" skillLevel="2" getLevel="90" levelUpSp="370000" />
		<skill skillName="Create Item" skillId="172" skillLevel="12" getLevel="90" autoGet="true" />
		<skill skillName="Death Strike" skillId="11511" skillLevel="4" getLevel="90" levelUpSp="370000" />
		<skill skillName="Transform" skillId="11537" skillLevel="4" getLevel="91" levelUpSp="400000" />
		<skill skillName="Shadow Blade" skillId="11510" skillLevel="4" getLevel="91" levelUpSp="400000" />
		<skill skillName="Petrify" skillId="11539" skillLevel="4" getLevel="91" levelUpSp="400000" />
		<skill skillName="Mass Shadow Blade" skillId="11514" skillLevel="4" getLevel="91" levelUpSp="400000" />
		<skill skillName="Crippling Attack" skillId="11509" skillLevel="5" getLevel="92" levelUpSp="420000" />
		<skill skillName="Divine Cancel" skillId="11536" skillLevel="4" getLevel="92" levelUpSp="420000" />
		<skill skillName="Mass Crippling Attack" skillId="11513" skillLevel="5" getLevel="92" levelUpSp="420000" />
		<skill skillName="Death Strike" skillId="11511" skillLevel="5" getLevel="92" levelUpSp="420000" />
		<skill skillName="Assault Rush" skillId="11508" skillLevel="4" getLevel="93" levelUpSp="440000" />
		<skill skillName="Shadow Blade" skillId="11510" skillLevel="5" getLevel="93" levelUpSp="440000" />
		<skill skillName="Petrify" skillId="11539" skillLevel="5" getLevel="93" levelUpSp="440000" />
		<skill skillName="Disperse" skillId="11543" skillLevel="1" getLevel="93" levelUpSp="440000" />
		<skill skillName="Angel's Touch" skillId="11534" skillLevel="3" getLevel="93" levelUpSp="440000" />
		<skill skillName="Mass Shadow Blade" skillId="11514" skillLevel="5" getLevel="93" levelUpSp="440000" />
		<skill skillName="Crippling Attack" skillId="11509" skillLevel="6" getLevel="94" levelUpSp="480000" />
		<skill skillName="Transform" skillId="11537" skillLevel="5" getLevel="94" levelUpSp="480000" />
		<skill skillName="Mass Crippling Attack" skillId="11513" skillLevel="6" getLevel="94" levelUpSp="480000" />
		<skill skillName="Death Strike" skillId="11511" skillLevel="6" getLevel="94" levelUpSp="480000" />
		<skill skillName="Superior Divine Lore" skillId="11552" skillLevel="3" getLevel="95" levelUpSp="1000000" />
		<skill skillName="Superior Advantage" skillId="11581" skillLevel="3" getLevel="95" levelUpSp="1000000" />
		<skill skillName="Angel's Resurrection" skillId="11564" skillLevel="3" getLevel="95" levelUpSp="1000000" />
		<skill skillName="Divine Cancel" skillId="11536" skillLevel="5" getLevel="95" levelUpSp="1000000" />
		<skill skillName="Giant Root" skillId="11561" skillLevel="3" getLevel="95" levelUpSp="1000000" />
		<skill skillName="Mass Transform" skillId="11580" skillLevel="3" getLevel="95" levelUpSp="1000000" />
		<skill skillName="Mass Giant Root" skillId="11538" skillLevel="3" getLevel="95" levelUpSp="1000000" />
		<skill skillName="Shadow Blade" skillId="11510" skillLevel="6" getLevel="95" levelUpSp="1000000" />
		<skill skillName="Quick Escape" skillId="11540" skillLevel="3" getLevel="95" levelUpSp="1000000" />
		<skill skillName="Crazy Nocturne" skillId="11545" skillLevel="1" getLevel="95" levelUpSp="1000000" />
		<skill skillName="Harp Melody" skillId="11521" skillLevel="3" getLevel="95" levelUpSp="1000000" />
		<skill skillName="Drum Melody" skillId="11518" skillLevel="3" getLevel="95" levelUpSp="1000000" />
		<skill skillName="Guitar Melody" skillId="11520" skillLevel="3" getLevel="95" levelUpSp="1000000" />
		<skill skillName="Lute Melody" skillId="11522" skillLevel="3" getLevel="95" levelUpSp="1000000" />
		<skill skillName="Pipe Organ Melody" skillId="11519" skillLevel="3" getLevel="95" levelUpSp="1000000" />
		<skill skillName="Horn Melody" skillId="11517" skillLevel="3" getLevel="95" levelUpSp="1000000" />
		<skill skillName="Petrify" skillId="11539" skillLevel="6" getLevel="95" levelUpSp="1000000" />
		<skill skillName="Create Item" skillId="172" skillLevel="13" getLevel="95" autoGet="true" />
		<skill skillName="Mass Shadow Blade" skillId="11514" skillLevel="6" getLevel="95" levelUpSp="1000000" />
		<skill skillName="Crippling Attack" skillId="11509" skillLevel="7" getLevel="96" levelUpSp="4970000" />
		<skill skillName="Assault Rush" skillId="11508" skillLevel="5" getLevel="96" levelUpSp="4970000" />
		<skill skillName="Mass Crippling Attack" skillId="11513" skillLevel="7" getLevel="96" levelUpSp="4970000" />
		<skill skillName="Disperse" skillId="11543" skillLevel="2" getLevel="96" levelUpSp="4970000" />
		<skill skillName="Angel's Touch" skillId="11534" skillLevel="4" getLevel="96" levelUpSp="4970000" />
		<skill skillName="Death Strike" skillId="11511" skillLevel="7" getLevel="96" levelUpSp="4970000" />
		<skill skillName="Transform" skillId="11537" skillLevel="6" getLevel="97" levelUpSp="4980000" />
		<skill skillName="Shadow Blade" skillId="11510" skillLevel="7" getLevel="97" levelUpSp="4980000" />
		<skill skillName="Petrify" skillId="11539" skillLevel="7" getLevel="97" levelUpSp="4980000" />
		<skill skillName="Blood Requiem" skillId="11533" skillLevel="1" getLevel="97" levelUpSp="4980000" />
		<skill skillName="Mass Shadow Blade" skillId="11514" skillLevel="7" getLevel="97" levelUpSp="4980000" />
		<skill skillName="Crippling Attack" skillId="11509" skillLevel="8" getLevel="98" levelUpSp="4990000" />
		<skill skillName="Divine Cancel" skillId="11536" skillLevel="6" getLevel="98" levelUpSp="4990000" />
		<skill skillName="Mass Crippling Attack" skillId="11513" skillLevel="8" getLevel="98" levelUpSp="4990000" />
		<skill skillName="Death Strike" skillId="11511" skillLevel="8" getLevel="98" levelUpSp="4990000" />
		<skill skillName="Assault Rush" skillId="11508" skillLevel="6" getLevel="99" levelUpSp="5000000" />
		<skill skillName="Superior Divine Lore" skillId="11552" skillLevel="4" getLevel="99" levelUpSp="5000000" />
		<skill skillName="Superior Advantage" skillId="11581" skillLevel="4" getLevel="99" levelUpSp="5000000" />
		<skill skillName="Giant Root" skillId="11561" skillLevel="4" getLevel="99" levelUpSp="5000000" />
		<skill skillName="Transform" skillId="11537" skillLevel="7" getLevel="99" levelUpSp="5000000" />
		<skill skillName="Mass Transform" skillId="11580" skillLevel="4" getLevel="99" levelUpSp="5000000" />
		<skill skillName="Mass Giant Root" skillId="11538" skillLevel="4" getLevel="99" levelUpSp="5000000" />
		<skill skillName="Shadow Blade" skillId="11510" skillLevel="8" getLevel="99" levelUpSp="5000000" />
		<skill skillName="Quick Escape" skillId="11540" skillLevel="4" getLevel="99" levelUpSp="5000000" />
		<skill skillName="Celestial Aegis" skillId="11560" skillLevel="2" getLevel="99" levelUpSp="5000000" />
		<skill skillName="Harp Melody" skillId="11521" skillLevel="4" getLevel="99" levelUpSp="5000000" />
		<skill skillName="Drum Melody" skillId="11518" skillLevel="4" getLevel="99" levelUpSp="5000000" />
		<skill skillName="Guitar Melody" skillId="11520" skillLevel="4" getLevel="99" levelUpSp="5000000" />
		<skill skillName="Lute Melody" skillId="11522" skillLevel="4" getLevel="99" levelUpSp="5000000" />
		<skill skillName="Pipe Organ Melody" skillId="11519" skillLevel="4" getLevel="99" levelUpSp="5000000" />
		<skill skillName="Horn Melody" skillId="11517" skillLevel="4" getLevel="99" levelUpSp="5000000" />
		<skill skillName="Petrify" skillId="11539" skillLevel="8" getLevel="99" levelUpSp="5000000" />
		<skill skillName="Disperse" skillId="11543" skillLevel="3" getLevel="99" levelUpSp="5000000" />
		<skill skillName="Angel's Touch" skillId="11534" skillLevel="5" getLevel="99" levelUpSp="5000000" />
		<skill skillName="Chaos Symphony" skillId="11546" skillLevel="1" getLevel="99" levelUpSp="5000000" />
		<skill skillName="Create Item" skillId="172" skillLevel="14" getLevel="99" autoGet="true" />
		<skill skillName="Mass Shadow Blade" skillId="11514" skillLevel="8" getLevel="99" levelUpSp="5000000" />
		
		<!-- Ertheia Update Skill -->
		<skill skillName="Battle Ditty" skillId="11615" skillLevel="1" getLevel="99" levelUpSp="5000000">
			<item id="39738" count="8" />
		</skill>
		<skill skillName="Protective Ditty" skillId="11616" skillLevel="1" getLevel="99" levelUpSp="5000000">
			<item id="39738" count="8" />
		</skill>

		<!-- Dual Maximum HP -->
		<skill skillName="Dual Maximum HP" skillId="1986" skillLevel="1" getLevel="85" getDualClassLevel="85" levelUpSp="10000" />
		<skill skillName="Dual Maximum HP" skillId="1986" skillLevel="2" getLevel="90" getDualClassLevel="90" levelUpSp="370000" />
		<skill skillName="Dual Maximum HP" skillId="1986" skillLevel="3" getLevel="95" getDualClassLevel="95" levelUpSp="1000000" />
		<skill skillName="Dual Maximum HP" skillId="1986" skillLevel="4" getLevel="99" getDualClassLevel="99" levelUpSp="5000000" />
	</skillTree>
</list>
