<?xml version="1.0" encoding="UTF-8"?>
<list xmlns:xsi="http://www.w3.org/2001/XMLSchema-instance" xsi:noNamespaceSchemaLocation="../../xsd/npcs.xsd">
	<npc id="23900" level="99" type="L2Npc" name="Laikel of Terror" title="Leader of Creation">
		<!-- AUTO GENERATED NPC TODO: FIX IT -->
		<race>HUMAN</race>
		<sex>FEMALE</sex>
		<stats str="40" int="21" dex="30" wit="20" con="43" men="10">
			<vitals hp="15841" hpRegen="10.5" mp="2355" mpRegen="3.6" />
			<speed>
				<walk ground="1" />
				<run ground="210" />
			</speed>
			<attack physical="1950.2231755595" magical="1331.5869440987" critical="4" attackSpeed="253" range="40" />
			<defence physical="405.85106382979" magical="297.0297029703" />
		</stats>
		<status attackable="false" />
		<skill_list>
			<skill id="4045" level="1" /> <!-- Full Magic Attack Resistance -->
		</skill_list>
		<collision>
			<radius normal="30" />
			<height normal="60" />
		</collision>
	</npc>
	<npc id="23901" level="99" type="L2Npc" name="Giant Spider of Terror" title="Leader of Creation">
		<!-- AUTO GENERATED NPC TODO: FIX IT -->
		<race>HUMAN</race>
		<sex>FEMALE</sex>
		<stats str="40" int="21" dex="30" wit="20" con="43" men="10">
			<vitals hp="15841" hpRegen="10.5" mp="2355" mpRegen="3.6" />
			<speed>
				<walk ground="1" />
				<run ground="210" />
			</speed>
			<attack physical="1950.2231755595" magical="1331.5869440987" critical="4" attackSpeed="253" range="40" />
			<defence physical="405.85106382979" magical="297.0297029703" />
		</stats>
		<status attackable="false" />
		<skill_list>
			<skill id="4045" level="1" /> <!-- Full Magic Attack Resistance -->
		</skill_list>
		<collision>
			<radius normal="30" />
			<height normal="60" />
		</collision>
	</npc>
	<npc id="23902" level="99" type="L2Npc" name="Riba of Terror" title="Leader of Creation">
		<!-- AUTO GENERATED NPC TODO: FIX IT -->
		<race>HUMAN</race>
		<sex>FEMALE</sex>
		<stats str="40" int="21" dex="30" wit="20" con="43" men="10">
			<vitals hp="15841" hpRegen="10.5" mp="2355" mpRegen="3.6" />
			<speed>
				<walk ground="1" />
				<run ground="210" />
			</speed>
			<attack physical="1950.2231755595" magical="1331.5869440987" critical="4" attackSpeed="253" range="40" />
			<defence physical="405.85106382979" magical="297.0297029703" />
		</stats>
		<status attackable="false" />
		<skill_list>
			<skill id="4045" level="1" /> <!-- Full Magic Attack Resistance -->
		</skill_list>
		<collision>
			<radius normal="30" />
			<height normal="60" />
		</collision>
	</npc>
	<npc id="23903" level="99" type="L2Npc" name="Stakato Worker">
		<!-- AUTO GENERATED NPC TODO: FIX IT -->
		<race>HUMAN</race>
		<sex>FEMALE</sex>
		<stats str="40" int="21" dex="30" wit="20" con="43" men="10">
			<vitals hp="15841" hpRegen="10.5" mp="2355" mpRegen="3.6" />
			<speed>
				<walk ground="1" />
				<run ground="210" />
			</speed>
			<attack physical="1950.2231755595" magical="1331.5869440987" critical="4" attackSpeed="253" range="40" />
			<defence physical="405.85106382979" magical="297.0297029703" />
		</stats>
		<status attackable="false" />
		<skill_list>
			<skill id="4045" level="1" /> <!-- Full Magic Attack Resistance -->
		</skill_list>
		<collision>
			<radius normal="30" />
			<height normal="60" />
		</collision>
	</npc>
	<npc id="23904" level="99" type="L2Npc" name="Stakato Guard">
		<!-- AUTO GENERATED NPC TODO: FIX IT -->
		<race>HUMAN</race>
		<sex>FEMALE</sex>
		<stats str="40" int="21" dex="30" wit="20" con="43" men="10">
			<vitals hp="15841" hpRegen="10.5" mp="2355" mpRegen="3.6" />
			<speed>
				<walk ground="1" />
				<run ground="210" />
			</speed>
			<attack physical="1950.2231755595" magical="1331.5869440987" critical="4" attackSpeed="253" range="40" />
			<defence physical="405.85106382979" magical="297.0297029703" />
		</stats>
		<status attackable="false" />
		<skill_list>
			<skill id="4045" level="1" /> <!-- Full Magic Attack Resistance -->
		</skill_list>
		<collision>
			<radius normal="30" />
			<height normal="60" />
		</collision>
	</npc>
	<npc id="23905" level="99" type="L2Npc" name="Stakato Invader" title="Stakato Leader">
		<!-- AUTO GENERATED NPC TODO: FIX IT -->
		<race>HUMAN</race>
		<sex>FEMALE</sex>
		<stats str="40" int="21" dex="30" wit="20" con="43" men="10">
			<vitals hp="15841" hpRegen="10.5" mp="2355" mpRegen="3.6" />
			<speed>
				<walk ground="1" />
				<run ground="210" />
			</speed>
			<attack physical="1950.2231755595" magical="1331.5869440987" critical="4" attackSpeed="253" range="40" />
			<defence physical="405.85106382979" magical="297.0297029703" />
		</stats>
		<status attackable="false" />
		<skill_list>
			<skill id="4045" level="1" /> <!-- Full Magic Attack Resistance -->
		</skill_list>
		<collision>
			<radius normal="30" />
			<height normal="60" />
		</collision>
	</npc>
	<npc id="23906" level="99" type="L2Npc" name="Stakato Queen" title="Stakato Leader">
		<!-- AUTO GENERATED NPC TODO: FIX IT -->
		<race>HUMAN</race>
		<sex>FEMALE</sex>
		<stats str="40" int="21" dex="30" wit="20" con="43" men="10">
			<vitals hp="15841" hpRegen="10.5" mp="2355" mpRegen="3.6" />
			<speed>
				<walk ground="1" />
				<run ground="210" />
			</speed>
			<attack physical="1950.2231755595" magical="1331.5869440987" critical="4" attackSpeed="253" range="40" />
			<defence physical="405.85106382979" magical="297.0297029703" />
		</stats>
		<status attackable="false" />
		<skill_list>
			<skill id="4045" level="1" /> <!-- Full Magic Attack Resistance -->
		</skill_list>
		<collision>
			<radius normal="30" />
			<height normal="60" />
		</collision>
	</npc>
	<npc id="23907" level="99" type="L2Npc" name="Ultimate Gatekeeper A1803-1" title="Gatekeeper Leader">
		<!-- AUTO GENERATED NPC TODO: FIX IT -->
		<race>HUMAN</race>
		<sex>FEMALE</sex>
		<stats str="40" int="21" dex="30" wit="20" con="43" men="10">
			<vitals hp="15841" hpRegen="10.5" mp="2355" mpRegen="3.6" />
			<speed>
				<walk ground="1" />
				<run ground="210" />
			</speed>
			<attack physical="1950.2231755595" magical="1331.5869440987" critical="4" attackSpeed="253" range="40" />
			<defence physical="405.85106382979" magical="297.0297029703" />
		</stats>
		<status attackable="false" />
		<skill_list>
			<skill id="4045" level="1" /> <!-- Full Magic Attack Resistance -->
		</skill_list>
		<collision>
			<radius normal="30" />
			<height normal="60" />
		</collision>
	</npc>
	<npc id="23908" level="99" type="L2Npc" name="Hell Assassin">
		<!-- AUTO GENERATED NPC TODO: FIX IT -->
		<race>HUMAN</race>
		<sex>FEMALE</sex>
		<stats str="40" int="21" dex="30" wit="20" con="43" men="10">
			<vitals hp="15841" hpRegen="10.5" mp="2355" mpRegen="3.6" />
			<speed>
				<walk ground="1" />
				<run ground="210" />
			</speed>
			<attack physical="1950.2231755595" magical="1331.5869440987" critical="4" attackSpeed="253" range="40" />
			<defence physical="405.85106382979" magical="297.0297029703" />
		</stats>
		<status attackable="false" />
		<skill_list>
			<skill id="4045" level="1" /> <!-- Full Magic Attack Resistance -->
		</skill_list>
		<collision>
			<radius normal="30" />
			<height normal="60" />
		</collision>
	</npc>
	<npc id="23909" level="99" type="L2Npc" name="Hell Dark Wizard">
		<!-- AUTO GENERATED NPC TODO: FIX IT -->
		<race>HUMAN</race>
		<sex>FEMALE</sex>
		<stats str="40" int="21" dex="30" wit="20" con="43" men="10">
			<vitals hp="15841" hpRegen="10.5" mp="2355" mpRegen="3.6" />
			<speed>
				<walk ground="1" />
				<run ground="210" />
			</speed>
			<attack physical="1950.2231755595" magical="1331.5869440987" critical="4" attackSpeed="253" range="40" />
			<defence physical="405.85106382979" magical="297.0297029703" />
		</stats>
		<status attackable="false" />
		<skill_list>
			<skill id="4045" level="1" /> <!-- Full Magic Attack Resistance -->
		</skill_list>
		<collision>
			<radius normal="30" />
			<height normal="60" />
		</collision>
	</npc>
	<npc id="23910" level="99" type="L2Npc" name="Hell Armor" title="u,Devil’s Advocate">
		<!-- AUTO GENERATED NPC TODO: FIX IT -->
		<race>HUMAN</race>
		<sex>FEMALE</sex>
		<stats str="40" int="21" dex="30" wit="20" con="43" men="10">
			<vitals hp="15841" hpRegen="10.5" mp="2355" mpRegen="3.6" />
			<speed>
				<walk ground="1" />
				<run ground="210" />
			</speed>
			<attack physical="1950.2231755595" magical="1331.5869440987" critical="4" attackSpeed="253" range="40" />
			<defence physical="405.85106382979" magical="297.0297029703" />
		</stats>
		<status attackable="false" />
		<skill_list>
			<skill id="4045" level="1" /> <!-- Full Magic Attack Resistance -->
		</skill_list>
		<collision>
			<radius normal="30" />
			<height normal="60" />
		</collision>
	</npc>
	<npc id="23911" level="99" type="L2Npc" name="Hell Queen" title="u,Devil’s Advocate">
		<!-- AUTO GENERATED NPC TODO: FIX IT -->
		<race>HUMAN</race>
		<sex>FEMALE</sex>
		<stats str="40" int="21" dex="30" wit="20" con="43" men="10">
			<vitals hp="15841" hpRegen="10.5" mp="2355" mpRegen="3.6" />
			<speed>
				<walk ground="1" />
				<run ground="210" />
			</speed>
			<attack physical="1950.2231755595" magical="1331.5869440987" critical="4" attackSpeed="253" range="40" />
			<defence physical="405.85106382979" magical="297.0297029703" />
		</stats>
		<status attackable="false" />
		<skill_list>
			<skill id="4045" level="1" /> <!-- Full Magic Attack Resistance -->
		</skill_list>
		<collision>
			<radius normal="30" />
			<height normal="60" />
		</collision>
	</npc>
	<npc id="23912" level="99" type="L2Npc" name="Hell Lord" title="u,Devil’s Advocate">
		<!-- AUTO GENERATED NPC TODO: FIX IT -->
		<race>HUMAN</race>
		<sex>FEMALE</sex>
		<stats str="40" int="21" dex="30" wit="20" con="43" men="10">
			<vitals hp="15841" hpRegen="10.5" mp="2355" mpRegen="3.6" />
			<speed>
				<walk ground="1" />
				<run ground="210" />
			</speed>
			<attack physical="1950.2231755595" magical="1331.5869440987" critical="4" attackSpeed="253" range="40" />
			<defence physical="405.85106382979" magical="297.0297029703" />
		</stats>
		<status attackable="false" />
		<skill_list>
			<skill id="4045" level="1" /> <!-- Full Magic Attack Resistance -->
		</skill_list>
		<collision>
			<radius normal="30" />
			<height normal="60" />
		</collision>
	</npc>
	<npc id="23913" level="99" type="L2Npc" name="Heavenly Soldier">
		<!-- AUTO GENERATED NPC TODO: FIX IT -->
		<race>HUMAN</race>
		<sex>FEMALE</sex>
		<stats str="40" int="21" dex="30" wit="20" con="43" men="10">
			<vitals hp="15841" hpRegen="10.5" mp="2355" mpRegen="3.6" />
			<speed>
				<walk ground="1" />
				<run ground="210" />
			</speed>
			<attack physical="1950.2231755595" magical="1331.5869440987" critical="4" attackSpeed="253" range="40" />
			<defence physical="405.85106382979" magical="297.0297029703" />
		</stats>
		<status attackable="false" />
		<skill_list>
			<skill id="4045" level="1" /> <!-- Full Magic Attack Resistance -->
		</skill_list>
		<collision>
			<radius normal="30" />
			<height normal="60" />
		</collision>
	</npc>
	<npc id="23914" level="99" type="L2Npc" name="Heavenly Priest">
		<!-- AUTO GENERATED NPC TODO: FIX IT -->
		<race>HUMAN</race>
		<sex>FEMALE</sex>
		<stats str="40" int="21" dex="30" wit="20" con="43" men="10">
			<vitals hp="15841" hpRegen="10.5" mp="2355" mpRegen="3.6" />
			<speed>
				<walk ground="1" />
				<run ground="210" />
			</speed>
			<attack physical="1950.2231755595" magical="1331.5869440987" critical="4" attackSpeed="253" range="40" />
			<defence physical="405.85106382979" magical="297.0297029703" />
		</stats>
		<status attackable="false" />
		<skill_list>
			<skill id="4045" level="1" /> <!-- Full Magic Attack Resistance -->
		</skill_list>
		<collision>
			<radius normal="30" />
			<height normal="60" />
		</collision>
	</npc>
	<npc id="23915" level="99" type="L2Npc" name="Heavenly Judge" title="u,Angel’s Advocate">
		<!-- AUTO GENERATED NPC TODO: FIX IT -->
		<race>HUMAN</race>
		<sex>FEMALE</sex>
		<stats str="40" int="21" dex="30" wit="20" con="43" men="10">
			<vitals hp="15841" hpRegen="10.5" mp="2355" mpRegen="3.6" />
			<speed>
				<walk ground="1" />
				<run ground="210" />
			</speed>
			<attack physical="1950.2231755595" magical="1331.5869440987" critical="4" attackSpeed="253" range="40" />
			<defence physical="405.85106382979" magical="297.0297029703" />
		</stats>
		<status attackable="false" />
		<skill_list>
			<skill id="4045" level="1" /> <!-- Full Magic Attack Resistance -->
		</skill_list>
		<collision>
			<radius normal="30" />
			<height normal="60" />
		</collision>
	</npc>
	<npc id="23916" level="99" type="L2Npc" name="Heavenly Wings">
		<!-- AUTO GENERATED NPC TODO: FIX IT -->
		<race>HUMAN</race>
		<sex>FEMALE</sex>
		<stats str="40" int="21" dex="30" wit="20" con="43" men="10">
			<vitals hp="15841" hpRegen="10.5" mp="2355" mpRegen="3.6" />
			<speed>
				<walk ground="1" />
				<run ground="210" />
			</speed>
			<attack physical="1950.2231755595" magical="1331.5869440987" critical="4" attackSpeed="253" range="40" />
			<defence physical="405.85106382979" magical="297.0297029703" />
		</stats>
		<status attackable="false" />
		<skill_list>
			<skill id="4045" level="1" /> <!-- Full Magic Attack Resistance -->
		</skill_list>
		<collision>
			<radius normal="30" />
			<height normal="60" />
		</collision>
	</npc>
	<npc id="23917" level="99" type="L2Npc" name="Heavenly Guardian" title="u,Angel’s Advocate">
		<!-- AUTO GENERATED NPC TODO: FIX IT -->
		<race>HUMAN</race>
		<sex>FEMALE</sex>
		<stats str="40" int="21" dex="30" wit="20" con="43" men="10">
			<vitals hp="15841" hpRegen="10.5" mp="2355" mpRegen="3.6" />
			<speed>
				<walk ground="1" />
				<run ground="210" />
			</speed>
			<attack physical="1950.2231755595" magical="1331.5869440987" critical="4" attackSpeed="253" range="40" />
			<defence physical="405.85106382979" magical="297.0297029703" />
		</stats>
		<status attackable="false" />
		<skill_list>
			<skill id="4045" level="1" /> <!-- Full Magic Attack Resistance -->
		</skill_list>
		<collision>
			<radius normal="30" />
			<height normal="60" />
		</collision>
	</npc>
	<npc id="23918" level="99" type="L2Npc" name="Drake">
		<!-- AUTO GENERATED NPC TODO: FIX IT -->
		<race>HUMAN</race>
		<sex>FEMALE</sex>
		<stats str="40" int="21" dex="30" wit="20" con="43" men="10">
			<vitals hp="15841" hpRegen="10.5" mp="2355" mpRegen="3.6" />
			<speed>
				<walk ground="1" />
				<run ground="210" />
			</speed>
			<attack physical="1950.2231755595" magical="1331.5869440987" critical="4" attackSpeed="253" range="40" />
			<defence physical="405.85106382979" magical="297.0297029703" />
		</stats>
		<status attackable="false" />
		<skill_list>
			<skill id="4045" level="1" /> <!-- Full Magic Attack Resistance -->
		</skill_list>
		<collision>
			<radius normal="30" />
			<height normal="60" />
		</collision>
	</npc>
	<npc id="23919" level="99" type="L2Npc" name="Mutated Drake">
		<!-- AUTO GENERATED NPC TODO: FIX IT -->
		<race>HUMAN</race>
		<sex>FEMALE</sex>
		<stats str="40" int="21" dex="30" wit="20" con="43" men="10">
			<vitals hp="15841" hpRegen="10.5" mp="2355" mpRegen="3.6" />
			<speed>
				<walk ground="1" />
				<run ground="210" />
			</speed>
			<attack physical="1950.2231755595" magical="1331.5869440987" critical="4" attackSpeed="253" range="40" />
			<defence physical="405.85106382979" magical="297.0297029703" />
		</stats>
		<status attackable="false" />
		<skill_list>
			<skill id="4045" level="1" /> <!-- Full Magic Attack Resistance -->
		</skill_list>
		<collision>
			<radius normal="30" />
			<height normal="60" />
		</collision>
	</npc>
	<npc id="23920" level="99" type="L2Npc" name="Drak" title="u,Dragon’s Advocate">
		<!-- AUTO GENERATED NPC TODO: FIX IT -->
		<race>HUMAN</race>
		<sex>FEMALE</sex>
		<stats str="40" int="21" dex="30" wit="20" con="43" men="10">
			<vitals hp="15841" hpRegen="10.5" mp="2355" mpRegen="3.6" />
			<speed>
				<walk ground="1" />
				<run ground="210" />
			</speed>
			<attack physical="1950.2231755595" magical="1331.5869440987" critical="4" attackSpeed="253" range="40" />
			<defence physical="405.85106382979" magical="297.0297029703" />
		</stats>
		<status attackable="false" />
		<skill_list>
			<skill id="4045" level="1" /> <!-- Full Magic Attack Resistance -->
		</skill_list>
		<collision>
			<radius normal="30" />
			<height normal="60" />
		</collision>
	</npc>
	<npc id="23921" level="99" type="L2Npc" name="Inferno Drake">
		<!-- AUTO GENERATED NPC TODO: FIX IT -->
		<race>HUMAN</race>
		<sex>FEMALE</sex>
		<stats str="40" int="21" dex="30" wit="20" con="43" men="10">
			<vitals hp="15841" hpRegen="10.5" mp="2355" mpRegen="3.6" />
			<speed>
				<walk ground="1" />
				<run ground="210" />
			</speed>
			<attack physical="1950.2231755595" magical="1331.5869440987" critical="4" attackSpeed="253" range="40" />
			<defence physical="405.85106382979" magical="297.0297029703" />
		</stats>
		<status attackable="false" />
		<skill_list>
			<skill id="4045" level="1" /> <!-- Full Magic Attack Resistance -->
		</skill_list>
		<collision>
			<radius normal="30" />
			<height normal="60" />
		</collision>
	</npc>
	<npc id="23922" level="99" type="L2Npc" name="Chaos Drake" title="u,Dragon’s Advocate">
		<!-- AUTO GENERATED NPC TODO: FIX IT -->
		<race>HUMAN</race>
		<sex>FEMALE</sex>
		<stats str="40" int="21" dex="30" wit="20" con="43" men="10">
			<vitals hp="15841" hpRegen="10.5" mp="2355" mpRegen="3.6" />
			<speed>
				<walk ground="1" />
				<run ground="210" />
			</speed>
			<attack physical="1950.2231755595" magical="1331.5869440987" critical="4" attackSpeed="253" range="40" />
			<defence physical="405.85106382979" magical="297.0297029703" />
		</stats>
		<status attackable="false" />
		<skill_list>
			<skill id="4045" level="1" /> <!-- Full Magic Attack Resistance -->
		</skill_list>
		<collision>
			<radius normal="30" />
			<height normal="60" />
		</collision>
	</npc>
	<npc id="23923" level="99" type="L2Npc" name="Velociraptor">
		<!-- AUTO GENERATED NPC TODO: FIX IT -->
		<race>HUMAN</race>
		<sex>FEMALE</sex>
		<stats str="40" int="21" dex="30" wit="20" con="43" men="10">
			<vitals hp="15841" hpRegen="10.5" mp="2355" mpRegen="3.6" />
			<speed>
				<walk ground="1" />
				<run ground="210" />
			</speed>
			<attack physical="1950.2231755595" magical="1331.5869440987" critical="4" attackSpeed="253" range="40" />
			<defence physical="405.85106382979" magical="297.0297029703" />
		</stats>
		<status attackable="false" />
		<skill_list>
			<skill id="4045" level="1" /> <!-- Full Magic Attack Resistance -->
		</skill_list>
		<collision>
			<radius normal="30" />
			<height normal="60" />
		</collision>
	</npc>
	<npc id="23924" level="99" type="L2Npc" name="Ornithomimus">
		<!-- AUTO GENERATED NPC TODO: FIX IT -->
		<race>HUMAN</race>
		<sex>FEMALE</sex>
		<stats str="40" int="21" dex="30" wit="20" con="43" men="10">
			<vitals hp="15841" hpRegen="10.5" mp="2355" mpRegen="3.6" />
			<speed>
				<walk ground="1" />
				<run ground="210" />
			</speed>
			<attack physical="1950.2231755595" magical="1331.5869440987" critical="4" attackSpeed="253" range="40" />
			<defence physical="405.85106382979" magical="297.0297029703" />
		</stats>
		<status attackable="false" />
		<skill_list>
			<skill id="4045" level="1" /> <!-- Full Magic Attack Resistance -->
		</skill_list>
		<collision>
			<radius normal="30" />
			<height normal="60" />
		</collision>
	</npc>
	<npc id="23925" level="99" type="L2Npc" name="Pterosaur" title="Dominator of the Wild">
		<!-- AUTO GENERATED NPC TODO: FIX IT -->
		<race>HUMAN</race>
		<sex>FEMALE</sex>
		<stats str="40" int="21" dex="30" wit="20" con="43" men="10">
			<vitals hp="15841" hpRegen="10.5" mp="2355" mpRegen="3.6" />
			<speed>
				<walk ground="1" />
				<run ground="210" />
			</speed>
			<attack physical="1950.2231755595" magical="1331.5869440987" critical="4" attackSpeed="253" range="40" />
			<defence physical="405.85106382979" magical="297.0297029703" />
		</stats>
		<status attackable="false" />
		<skill_list>
			<skill id="4045" level="1" /> <!-- Full Magic Attack Resistance -->
		</skill_list>
		<collision>
			<radius normal="30" />
			<height normal="60" />
		</collision>
	</npc>
	<npc id="23926" level="99" type="L2Npc" name="Primeval Strider">
		<!-- AUTO GENERATED NPC TODO: FIX IT -->
		<race>HUMAN</race>
		<sex>FEMALE</sex>
		<stats str="40" int="21" dex="30" wit="20" con="43" men="10">
			<vitals hp="15841" hpRegen="10.5" mp="2355" mpRegen="3.6" />
			<speed>
				<walk ground="1" />
				<run ground="210" />
			</speed>
			<attack physical="1950.2231755595" magical="1331.5869440987" critical="4" attackSpeed="253" range="40" />
			<defence physical="405.85106382979" magical="297.0297029703" />
		</stats>
		<status attackable="false" />
		<skill_list>
			<skill id="4045" level="1" /> <!-- Full Magic Attack Resistance -->
		</skill_list>
		<collision>
			<radius normal="30" />
			<height normal="60" />
		</collision>
	</npc>
	<npc id="23927" level="99" type="L2Npc" name="Tyrannosaurus" title="Dominator of the Wild">
		<!-- AUTO GENERATED NPC TODO: FIX IT -->
		<race>HUMAN</race>
		<sex>FEMALE</sex>
		<stats str="40" int="21" dex="30" wit="20" con="43" men="10">
			<vitals hp="15841" hpRegen="10.5" mp="2355" mpRegen="3.6" />
			<speed>
				<walk ground="1" />
				<run ground="210" />
			</speed>
			<attack physical="1950.2231755595" magical="1331.5869440987" critical="4" attackSpeed="253" range="40" />
			<defence physical="405.85106382979" magical="297.0297029703" />
		</stats>
		<status attackable="false" />
		<skill_list>
			<skill id="4045" level="1" /> <!-- Full Magic Attack Resistance -->
		</skill_list>
		<collision>
			<radius normal="30" />
			<height normal="60" />
		</collision>
	</npc>
	<npc id="23928" level="99" type="L2Npc" name="Giant Golden Pig of Good Fortune" title="Intruding Challenger">
		<!-- AUTO GENERATED NPC TODO: FIX IT -->
		<race>HUMAN</race>
		<sex>FEMALE</sex>
		<stats str="40" int="21" dex="30" wit="20" con="43" men="10">
			<vitals hp="15841" hpRegen="10.5" mp="2355" mpRegen="3.6" />
			<speed>
				<walk ground="1" />
				<run ground="210" />
			</speed>
			<attack physical="1950.2231755595" magical="1331.5869440987" critical="4" attackSpeed="253" range="40" />
			<defence physical="405.85106382979" magical="297.0297029703" />
		</stats>
		<status attackable="false" />
		<skill_list>
			<skill id="4045" level="1" /> <!-- Full Magic Attack Resistance -->
		</skill_list>
		<collision>
			<radius normal="30" />
			<height normal="60" />
		</collision>
	</npc>
	<npc id="23929" level="99" type="L2Npc" name="Dancing Bard" title="Intruding Challenger">
		<!-- AUTO GENERATED NPC TODO: FIX IT -->
		<race>HUMAN</race>
		<sex>FEMALE</sex>
		<stats str="40" int="21" dex="30" wit="20" con="43" men="10">
			<vitals hp="15841" hpRegen="10.5" mp="2355" mpRegen="3.6" />
			<speed>
				<walk ground="1" />
				<run ground="210" />
			</speed>
			<attack physical="1950.2231755595" magical="1331.5869440987" critical="4" attackSpeed="253" range="40" />
			<defence physical="405.85106382979" magical="297.0297029703" />
		</stats>
		<status attackable="false" />
		<skill_list>
			<skill id="4045" level="1" /> <!-- Full Magic Attack Resistance -->
		</skill_list>
		<collision>
			<radius normal="30" />
			<height normal="60" />
		</collision>
	</npc>
	<npc id="23930" level="99" type="L2Npc" name="Gatekeeper Roxxy" title="Intruding Challenger">
		<!-- AUTO GENERATED NPC TODO: FIX IT -->
		<race>HUMAN</race>
		<sex>FEMALE</sex>
		<stats str="40" int="21" dex="30" wit="20" con="43" men="10">
			<vitals hp="15841" hpRegen="10.5" mp="2355" mpRegen="3.6" />
			<speed>
				<walk ground="1" />
				<run ground="210" />
			</speed>
			<attack physical="1950.2231755595" magical="1331.5869440987" critical="4" attackSpeed="253" range="40" />
			<defence physical="405.85106382979" magical="297.0297029703" />
		</stats>
		<status attackable="false" />
		<skill_list>
			<skill id="4045" level="1" /> <!-- Full Magic Attack Resistance -->
		</skill_list>
		<collision>
			<radius normal="30" />
			<height normal="60" />
		</collision>
	</npc>
	<npc id="23931" level="99" type="L2Npc" name="Super Kat the Cat" title="Intruding Challenger">
		<!-- AUTO GENERATED NPC TODO: FIX IT -->
		<race>HUMAN</race>
		<sex>FEMALE</sex>
		<stats str="40" int="21" dex="30" wit="20" con="43" men="10">
			<vitals hp="15841" hpRegen="10.5" mp="2355" mpRegen="3.6" />
			<speed>
				<walk ground="1" />
				<run ground="210" />
			</speed>
			<attack physical="1950.2231755595" magical="1331.5869440987" critical="4" attackSpeed="253" range="40" />
			<defence physical="405.85106382979" magical="297.0297029703" />
		</stats>
		<status attackable="false" />
		<skill_list>
			<skill id="4045" level="1" /> <!-- Full Magic Attack Resistance -->
		</skill_list>
		<collision>
			<radius normal="30" />
			<height normal="60" />
		</collision>
	</npc>
	<npc id="23932" level="99" type="L2Npc" name="Super Mew the Cat" title="Intruding Challenger">
		<!-- AUTO GENERATED NPC TODO: FIX IT -->
		<race>HUMAN</race>
		<sex>FEMALE</sex>
		<stats str="40" int="21" dex="30" wit="20" con="43" men="10">
			<vitals hp="15841" hpRegen="10.5" mp="2355" mpRegen="3.6" />
			<speed>
				<walk ground="1" />
				<run ground="210" />
			</speed>
			<attack physical="1950.2231755595" magical="1331.5869440987" critical="4" attackSpeed="253" range="40" />
			<defence physical="405.85106382979" magical="297.0297029703" />
		</stats>
		<status attackable="false" />
		<skill_list>
			<skill id="4045" level="1" /> <!-- Full Magic Attack Resistance -->
		</skill_list>
		<collision>
			<radius normal="30" />
			<height normal="60" />
		</collision>
	</npc>
	<npc id="23933" level="99" type="L2Npc" name="Super Queen the Cat" title="Intruding Challenger">
		<!-- AUTO GENERATED NPC TODO: FIX IT -->
		<race>HUMAN</race>
		<sex>FEMALE</sex>
		<stats str="40" int="21" dex="30" wit="20" con="43" men="10">
			<vitals hp="15841" hpRegen="10.5" mp="2355" mpRegen="3.6" />
			<speed>
				<walk ground="1" />
				<run ground="210" />
			</speed>
			<attack physical="1950.2231755595" magical="1331.5869440987" critical="4" attackSpeed="253" range="40" />
			<defence physical="405.85106382979" magical="297.0297029703" />
		</stats>
		<status attackable="false" />
		<skill_list>
			<skill id="4045" level="1" /> <!-- Full Magic Attack Resistance -->
		</skill_list>
		<collision>
			<radius normal="30" />
			<height normal="60" />
		</collision>
	</npc>
	<npc id="23934" level="99" type="L2Npc" name="Roa" title="Intruding Challenger">
		<!-- AUTO GENERATED NPC TODO: FIX IT -->
		<race>HUMAN</race>
		<sex>FEMALE</sex>
		<stats str="40" int="21" dex="30" wit="20" con="43" men="10">
			<vitals hp="15841" hpRegen="10.5" mp="2355" mpRegen="3.6" />
			<speed>
				<walk ground="1" />
				<run ground="210" />
			</speed>
			<attack physical="1950.2231755595" magical="1331.5869440987" critical="4" attackSpeed="253" range="40" />
			<defence physical="405.85106382979" magical="297.0297029703" />
		</stats>
		<status attackable="false" />
		<skill_list>
			<skill id="4045" level="1" /> <!-- Full Magic Attack Resistance -->
		</skill_list>
		<collision>
			<radius normal="30" />
			<height normal="60" />
		</collision>
	</npc>
	<npc id="23935" level="99" type="L2Npc" name="Golden Bat Dandy" title="Intruding Challenger">
		<!-- AUTO GENERATED NPC TODO: FIX IT -->
		<race>HUMAN</race>
		<sex>FEMALE</sex>
		<stats str="40" int="21" dex="30" wit="20" con="43" men="10">
			<vitals hp="15841" hpRegen="10.5" mp="2355" mpRegen="3.6" />
			<speed>
				<walk ground="1" />
				<run ground="210" />
			</speed>
			<attack physical="1950.2231755595" magical="1331.5869440987" critical="4" attackSpeed="253" range="40" />
			<defence physical="405.85106382979" magical="297.0297029703" />
		</stats>
		<status attackable="false" />
		<skill_list>
			<skill id="4045" level="1" /> <!-- Full Magic Attack Resistance -->
		</skill_list>
		<collision>
			<radius normal="30" />
			<height normal="60" />
		</collision>
	</npc>
	<npc id="23936" level="99" type="L2Npc" name="Ketra Knight Recruit">
		<!-- AUTO GENERATED NPC TODO: FIX IT -->
		<race>HUMAN</race>
		<sex>FEMALE</sex>
		<stats str="40" int="21" dex="30" wit="20" con="43" men="10">
			<vitals hp="15841" hpRegen="10.5" mp="2355" mpRegen="3.6" />
			<speed>
				<walk ground="1" />
				<run ground="210" />
			</speed>
			<attack physical="1950.2231755595" magical="1331.5869440987" critical="4" attackSpeed="253" range="40" />
			<defence physical="405.85106382979" magical="297.0297029703" />
		</stats>
		<status attackable="false" />
		<skill_list>
			<skill id="4045" level="1" /> <!-- Full Magic Attack Resistance -->
		</skill_list>
		<collision>
			<radius normal="30" />
			<height normal="60" />
		</collision>
	</npc>
	<npc id="23937" level="99" type="L2Npc" name="Kel Mahum Knight Recruit">
		<!-- AUTO GENERATED NPC TODO: FIX IT -->
		<race>HUMAN</race>
		<sex>FEMALE</sex>
		<stats str="40" int="21" dex="30" wit="20" con="43" men="10">
			<vitals hp="15841" hpRegen="10.5" mp="2355" mpRegen="3.6" />
			<speed>
				<walk ground="1" />
				<run ground="210" />
			</speed>
			<attack physical="1950.2231755595" magical="1331.5869440987" critical="4" attackSpeed="253" range="40" />
			<defence physical="405.85106382979" magical="297.0297029703" />
		</stats>
		<status attackable="false" />
		<skill_list>
			<skill id="4045" level="1" /> <!-- Full Magic Attack Resistance -->
		</skill_list>
		<collision>
			<radius normal="30" />
			<height normal="60" />
		</collision>
	</npc>
	<npc id="23938" level="99" type="L2Npc" name="Doom Wraith">
		<!-- AUTO GENERATED NPC TODO: FIX IT -->
		<race>HUMAN</race>
		<sex>FEMALE</sex>
		<stats str="40" int="21" dex="30" wit="20" con="43" men="10">
			<vitals hp="15841" hpRegen="10.5" mp="2355" mpRegen="3.6" />
			<speed>
				<walk ground="1" />
				<run ground="210" />
			</speed>
			<attack physical="1950.2231755595" magical="1331.5869440987" critical="4" attackSpeed="253" range="40" />
			<defence physical="405.85106382979" magical="297.0297029703" />
		</stats>
		<status attackable="false" />
		<skill_list>
			<skill id="4045" level="1" /> <!-- Full Magic Attack Resistance -->
		</skill_list>
		<collision>
			<radius normal="30" />
			<height normal="60" />
		</collision>
	</npc>
	<npc id="23939" level="99" type="L2Npc" name="Tanta Knight Recruit">
		<!-- AUTO GENERATED NPC TODO: FIX IT -->
		<race>HUMAN</race>
		<sex>FEMALE</sex>
		<stats str="40" int="21" dex="30" wit="20" con="43" men="10">
			<vitals hp="15841" hpRegen="10.5" mp="2355" mpRegen="3.6" />
			<speed>
				<walk ground="1" />
				<run ground="210" />
			</speed>
			<attack physical="1950.2231755595" magical="1331.5869440987" critical="4" attackSpeed="253" range="40" />
			<defence physical="405.85106382979" magical="297.0297029703" />
		</stats>
		<status attackable="false" />
		<skill_list>
			<skill id="4045" level="1" /> <!-- Full Magic Attack Resistance -->
		</skill_list>
		<collision>
			<radius normal="30" />
			<height normal="60" />
		</collision>
	</npc>
	<npc id="23940" level="99" type="L2Npc" name="Beetle of Terror">
		<!-- AUTO GENERATED NPC TODO: FIX IT -->
		<race>HUMAN</race>
		<sex>FEMALE</sex>
		<stats str="40" int="21" dex="30" wit="20" con="43" men="10">
			<vitals hp="15841" hpRegen="10.5" mp="2355" mpRegen="3.6" />
			<speed>
				<walk ground="1" />
				<run ground="210" />
			</speed>
			<attack physical="1950.2231755595" magical="1331.5869440987" critical="4" attackSpeed="253" range="40" />
			<defence physical="405.85106382979" magical="297.0297029703" />
		</stats>
		<status attackable="false" />
		<skill_list>
			<skill id="4045" level="1" /> <!-- Full Magic Attack Resistance -->
		</skill_list>
		<collision>
			<radius normal="30" />
			<height normal="60" />
		</collision>
	</npc>
	<npc id="23941" level="99" type="L2Npc" name="Stakato Knight Recruit">
		<!-- AUTO GENERATED NPC TODO: FIX IT -->
		<race>HUMAN</race>
		<sex>FEMALE</sex>
		<stats str="40" int="21" dex="30" wit="20" con="43" men="10">
			<vitals hp="15841" hpRegen="10.5" mp="2355" mpRegen="3.6" />
			<speed>
				<walk ground="1" />
				<run ground="210" />
			</speed>
			<attack physical="1950.2231755595" magical="1331.5869440987" critical="4" attackSpeed="253" range="40" />
			<defence physical="405.85106382979" magical="297.0297029703" />
		</stats>
		<status attackable="false" />
		<skill_list>
			<skill id="4045" level="1" /> <!-- Full Magic Attack Resistance -->
		</skill_list>
		<collision>
			<radius normal="30" />
			<height normal="60" />
		</collision>
	</npc>
	<npc id="23942" level="99" type="L2Npc" name="Hell Knight Recruit">
		<!-- AUTO GENERATED NPC TODO: FIX IT -->
		<race>HUMAN</race>
		<sex>FEMALE</sex>
		<stats str="40" int="21" dex="30" wit="20" con="43" men="10">
			<vitals hp="15841" hpRegen="10.5" mp="2355" mpRegen="3.6" />
			<speed>
				<walk ground="1" />
				<run ground="210" />
			</speed>
			<attack physical="1950.2231755595" magical="1331.5869440987" critical="4" attackSpeed="253" range="40" />
			<defence physical="405.85106382979" magical="297.0297029703" />
		</stats>
		<status attackable="false" />
		<skill_list>
			<skill id="4045" level="1" /> <!-- Full Magic Attack Resistance -->
		</skill_list>
		<collision>
			<radius normal="30" />
			<height normal="60" />
		</collision>
	</npc>
	<npc id="23943" level="99" type="L2Npc" name="Heavenly Guardian">
		<!-- AUTO GENERATED NPC TODO: FIX IT -->
		<race>HUMAN</race>
		<sex>FEMALE</sex>
		<stats str="40" int="21" dex="30" wit="20" con="43" men="10">
			<vitals hp="15841" hpRegen="10.5" mp="2355" mpRegen="3.6" />
			<speed>
				<walk ground="1" />
				<run ground="210" />
			</speed>
			<attack physical="1950.2231755595" magical="1331.5869440987" critical="4" attackSpeed="253" range="40" />
			<defence physical="405.85106382979" magical="297.0297029703" />
		</stats>
		<status attackable="false" />
		<skill_list>
			<skill id="4045" level="1" /> <!-- Full Magic Attack Resistance -->
		</skill_list>
		<collision>
			<radius normal="30" />
			<height normal="60" />
		</collision>
	</npc>
	<npc id="23944" level="99" type="L2Npc" name="Drake Knight Recruit">
		<!-- AUTO GENERATED NPC TODO: FIX IT -->
		<race>HUMAN</race>
		<sex>FEMALE</sex>
		<stats str="40" int="21" dex="30" wit="20" con="43" men="10">
			<vitals hp="15841" hpRegen="10.5" mp="2355" mpRegen="3.6" />
			<speed>
				<walk ground="1" />
				<run ground="210" />
			</speed>
			<attack physical="1950.2231755595" magical="1331.5869440987" critical="4" attackSpeed="253" range="40" />
			<defence physical="405.85106382979" magical="297.0297029703" />
		</stats>
		<status attackable="false" />
		<skill_list>
			<skill id="4045" level="1" /> <!-- Full Magic Attack Resistance -->
		</skill_list>
		<collision>
			<radius normal="30" />
			<height normal="60" />
		</collision>
	</npc>
	<npc id="23945" level="99" type="L2Npc" name="Velociraptor Protector Tree">
		<!-- AUTO GENERATED NPC TODO: FIX IT -->
		<race>HUMAN</race>
		<sex>FEMALE</sex>
		<stats str="40" int="21" dex="30" wit="20" con="43" men="10">
			<vitals hp="15841" hpRegen="10.5" mp="2355" mpRegen="3.6" />
			<speed>
				<walk ground="1" />
				<run ground="210" />
			</speed>
			<attack physical="1950.2231755595" magical="1331.5869440987" critical="4" attackSpeed="253" range="40" />
			<defence physical="405.85106382979" magical="297.0297029703" />
		</stats>
		<status attackable="false" />
		<skill_list>
			<skill id="4045" level="1" /> <!-- Full Magic Attack Resistance -->
		</skill_list>
		<collision>
			<radius normal="30" />
			<height normal="60" />
		</collision>
	</npc>
	<npc id="23946" level="99" type="L2Npc" name="Ketra Knight Recruit">
		<!-- AUTO GENERATED NPC TODO: FIX IT -->
		<race>HUMAN</race>
		<sex>FEMALE</sex>
		<stats str="40" int="21" dex="30" wit="20" con="43" men="10">
			<vitals hp="15841" hpRegen="10.5" mp="2355" mpRegen="3.6" />
			<speed>
				<walk ground="1" />
				<run ground="210" />
			</speed>
			<attack physical="1950.2231755595" magical="1331.5869440987" critical="4" attackSpeed="253" range="40" />
			<defence physical="405.85106382979" magical="297.0297029703" />
		</stats>
		<status attackable="false" />
		<skill_list>
			<skill id="4045" level="1" /> <!-- Full Magic Attack Resistance -->
		</skill_list>
		<collision>
			<radius normal="30" />
			<height normal="60" />
		</collision>
	</npc>
	<npc id="23947" level="99" type="L2Npc" name="Kel Mahum Knight Recruit">
		<!-- AUTO GENERATED NPC TODO: FIX IT -->
		<race>HUMAN</race>
		<sex>FEMALE</sex>
		<stats str="40" int="21" dex="30" wit="20" con="43" men="10">
			<vitals hp="15841" hpRegen="10.5" mp="2355" mpRegen="3.6" />
			<speed>
				<walk ground="1" />
				<run ground="210" />
			</speed>
			<attack physical="1950.2231755595" magical="1331.5869440987" critical="4" attackSpeed="253" range="40" />
			<defence physical="405.85106382979" magical="297.0297029703" />
		</stats>
		<status attackable="false" />
		<skill_list>
			<skill id="4045" level="1" /> <!-- Full Magic Attack Resistance -->
		</skill_list>
		<collision>
			<radius normal="30" />
			<height normal="60" />
		</collision>
	</npc>
	<npc id="23948" level="99" type="L2Npc" name="Doom Wraith">
		<!-- AUTO GENERATED NPC TODO: FIX IT -->
		<race>HUMAN</race>
		<sex>FEMALE</sex>
		<stats str="40" int="21" dex="30" wit="20" con="43" men="10">
			<vitals hp="15841" hpRegen="10.5" mp="2355" mpRegen="3.6" />
			<speed>
				<walk ground="1" />
				<run ground="210" />
			</speed>
			<attack physical="1950.2231755595" magical="1331.5869440987" critical="4" attackSpeed="253" range="40" />
			<defence physical="405.85106382979" magical="297.0297029703" />
		</stats>
		<status attackable="false" />
		<skill_list>
			<skill id="4045" level="1" /> <!-- Full Magic Attack Resistance -->
		</skill_list>
		<collision>
			<radius normal="30" />
			<height normal="60" />
		</collision>
	</npc>
	<npc id="23949" level="99" type="L2Npc" name="Tanta Knight Recruit">
		<!-- AUTO GENERATED NPC TODO: FIX IT -->
		<race>HUMAN</race>
		<sex>FEMALE</sex>
		<stats str="40" int="21" dex="30" wit="20" con="43" men="10">
			<vitals hp="15841" hpRegen="10.5" mp="2355" mpRegen="3.6" />
			<speed>
				<walk ground="1" />
				<run ground="210" />
			</speed>
			<attack physical="1950.2231755595" magical="1331.5869440987" critical="4" attackSpeed="253" range="40" />
			<defence physical="405.85106382979" magical="297.0297029703" />
		</stats>
		<status attackable="false" />
		<skill_list>
			<skill id="4045" level="1" /> <!-- Full Magic Attack Resistance -->
		</skill_list>
		<collision>
			<radius normal="30" />
			<height normal="60" />
		</collision>
	</npc>
	<npc id="23950" level="99" type="L2Npc" name="Beetle of Terror">
		<!-- AUTO GENERATED NPC TODO: FIX IT -->
		<race>HUMAN</race>
		<sex>FEMALE</sex>
		<stats str="40" int="21" dex="30" wit="20" con="43" men="10">
			<vitals hp="15841" hpRegen="10.5" mp="2355" mpRegen="3.6" />
			<speed>
				<walk ground="1" />
				<run ground="210" />
			</speed>
			<attack physical="1950.2231755595" magical="1331.5869440987" critical="4" attackSpeed="253" range="40" />
			<defence physical="405.85106382979" magical="297.0297029703" />
		</stats>
		<status attackable="false" />
		<skill_list>
			<skill id="4045" level="1" /> <!-- Full Magic Attack Resistance -->
		</skill_list>
		<collision>
			<radius normal="30" />
			<height normal="60" />
		</collision>
	</npc>
	<npc id="23951" level="99" type="L2Npc" name="Stakato Knight Recruit">
		<!-- AUTO GENERATED NPC TODO: FIX IT -->
		<race>HUMAN</race>
		<sex>FEMALE</sex>
		<stats str="40" int="21" dex="30" wit="20" con="43" men="10">
			<vitals hp="15841" hpRegen="10.5" mp="2355" mpRegen="3.6" />
			<speed>
				<walk ground="1" />
				<run ground="210" />
			</speed>
			<attack physical="1950.2231755595" magical="1331.5869440987" critical="4" attackSpeed="253" range="40" />
			<defence physical="405.85106382979" magical="297.0297029703" />
		</stats>
		<status attackable="false" />
		<skill_list>
			<skill id="4045" level="1" /> <!-- Full Magic Attack Resistance -->
		</skill_list>
		<collision>
			<radius normal="30" />
			<height normal="60" />
		</collision>
	</npc>
	<npc id="23952" level="99" type="L2Npc" name="Hell Knight Recruit">
		<!-- AUTO GENERATED NPC TODO: FIX IT -->
		<race>HUMAN</race>
		<sex>FEMALE</sex>
		<stats str="40" int="21" dex="30" wit="20" con="43" men="10">
			<vitals hp="15841" hpRegen="10.5" mp="2355" mpRegen="3.6" />
			<speed>
				<walk ground="1" />
				<run ground="210" />
			</speed>
			<attack physical="1950.2231755595" magical="1331.5869440987" critical="4" attackSpeed="253" range="40" />
			<defence physical="405.85106382979" magical="297.0297029703" />
		</stats>
		<status attackable="false" />
		<skill_list>
			<skill id="4045" level="1" /> <!-- Full Magic Attack Resistance -->
		</skill_list>
		<collision>
			<radius normal="30" />
			<height normal="60" />
		</collision>
	</npc>
	<npc id="23953" level="99" type="L2Npc" name="Heavenly Guardian">
		<!-- AUTO GENERATED NPC TODO: FIX IT -->
		<race>HUMAN</race>
		<sex>FEMALE</sex>
		<stats str="40" int="21" dex="30" wit="20" con="43" men="10">
			<vitals hp="15841" hpRegen="10.5" mp="2355" mpRegen="3.6" />
			<speed>
				<walk ground="1" />
				<run ground="210" />
			</speed>
			<attack physical="1950.2231755595" magical="1331.5869440987" critical="4" attackSpeed="253" range="40" />
			<defence physical="405.85106382979" magical="297.0297029703" />
		</stats>
		<status attackable="false" />
		<skill_list>
			<skill id="4045" level="1" /> <!-- Full Magic Attack Resistance -->
		</skill_list>
		<collision>
			<radius normal="30" />
			<height normal="60" />
		</collision>
	</npc>
	<npc id="23954" level="99" type="L2Npc" name="Drake Knight Recruit">
		<!-- AUTO GENERATED NPC TODO: FIX IT -->
		<race>HUMAN</race>
		<sex>FEMALE</sex>
		<stats str="40" int="21" dex="30" wit="20" con="43" men="10">
			<vitals hp="15841" hpRegen="10.5" mp="2355" mpRegen="3.6" />
			<speed>
				<walk ground="1" />
				<run ground="210" />
			</speed>
			<attack physical="1950.2231755595" magical="1331.5869440987" critical="4" attackSpeed="253" range="40" />
			<defence physical="405.85106382979" magical="297.0297029703" />
		</stats>
		<status attackable="false" />
		<skill_list>
			<skill id="4045" level="1" /> <!-- Full Magic Attack Resistance -->
		</skill_list>
		<collision>
			<radius normal="30" />
			<height normal="60" />
		</collision>
	</npc>
	<npc id="23955" level="99" type="L2Npc" name="Velociraptor Protector Tree">
		<!-- AUTO GENERATED NPC TODO: FIX IT -->
		<race>HUMAN</race>
		<sex>FEMALE</sex>
		<stats str="40" int="21" dex="30" wit="20" con="43" men="10">
			<vitals hp="15841" hpRegen="10.5" mp="2355" mpRegen="3.6" />
			<speed>
				<walk ground="1" />
				<run ground="210" />
			</speed>
			<attack physical="1950.2231755595" magical="1331.5869440987" critical="4" attackSpeed="253" range="40" />
			<defence physical="405.85106382979" magical="297.0297029703" />
		</stats>
		<status attackable="false" />
		<skill_list>
			<skill id="4045" level="1" /> <!-- Full Magic Attack Resistance -->
		</skill_list>
		<collision>
			<radius normal="30" />
			<height normal="60" />
		</collision>
	</npc>
	<npc id="23956" level="99" type="L2Npc" name="Veil Master" title="Aide of the Blood Queen">
		<!-- AUTO GENERATED NPC TODO: FIX IT -->
		<race>HUMAN</race>
		<sex>FEMALE</sex>
		<stats str="40" int="21" dex="30" wit="20" con="43" men="10">
			<vitals hp="15841" hpRegen="10.5" mp="2355" mpRegen="3.6" />
			<speed>
				<walk ground="1" />
				<run ground="210" />
			</speed>
			<attack physical="1950.2231755595" magical="1331.5869440987" critical="4" attackSpeed="253" range="40" />
			<defence physical="405.85106382979" magical="297.0297029703" />
		</stats>
		<status attackable="false" />
		<skill_list>
			<skill id="4045" level="1" /> <!-- Full Magic Attack Resistance -->
		</skill_list>
		<collision>
			<radius normal="30" />
			<height normal="60" />
		</collision>
	</npc>
	<npc id="23957" level="99" type="L2Npc" name="Tanta Healer" title="u,Commander’s Medic">
		<!-- AUTO GENERATED NPC TODO: FIX IT -->
		<race>HUMAN</race>
		<sex>FEMALE</sex>
		<stats str="40" int="21" dex="30" wit="20" con="43" men="10">
			<vitals hp="15841" hpRegen="10.5" mp="2355" mpRegen="3.6" />
			<speed>
				<walk ground="1" />
				<run ground="210" />
			</speed>
			<attack physical="1950.2231755595" magical="1331.5869440987" critical="4" attackSpeed="253" range="40" />
			<defence physical="405.85106382979" magical="297.0297029703" />
		</stats>
		<status attackable="false" />
		<skill_list>
			<skill id="4045" level="1" /> <!-- Full Magic Attack Resistance -->
		</skill_list>
		<collision>
			<radius normal="30" />
			<height normal="60" />
		</collision>
	</npc>
	<npc id="23958" level="99" type="L2Npc" name="Young Poisonous Spider">
		<!-- AUTO GENERATED NPC TODO: FIX IT -->
		<race>HUMAN</race>
		<sex>FEMALE</sex>
		<stats str="40" int="21" dex="30" wit="20" con="43" men="10">
			<vitals hp="15841" hpRegen="10.5" mp="2355" mpRegen="3.6" />
			<speed>
				<walk ground="1" />
				<run ground="210" />
			</speed>
			<attack physical="1950.2231755595" magical="1331.5869440987" critical="4" attackSpeed="253" range="40" />
			<defence physical="405.85106382979" magical="297.0297029703" />
		</stats>
		<status attackable="false" />
		<skill_list>
			<skill id="4045" level="1" /> <!-- Full Magic Attack Resistance -->
		</skill_list>
		<collision>
			<radius normal="30" />
			<height normal="60" />
		</collision>
	</npc>
	<npc id="23959" level="99" type="L2Npc" name="Young Stakato">
		<!-- AUTO GENERATED NPC TODO: FIX IT -->
		<race>HUMAN</race>
		<sex>FEMALE</sex>
		<stats str="40" int="21" dex="30" wit="20" con="43" men="10">
			<vitals hp="15841" hpRegen="10.5" mp="2355" mpRegen="3.6" />
			<speed>
				<walk ground="1" />
				<run ground="210" />
			</speed>
			<attack physical="1950.2231755595" magical="1331.5869440987" critical="4" attackSpeed="253" range="40" />
			<defence physical="405.85106382979" magical="297.0297029703" />
		</stats>
		<status attackable="false" />
		<skill_list>
			<skill id="4045" level="1" /> <!-- Full Magic Attack Resistance -->
		</skill_list>
		<collision>
			<radius normal="30" />
			<height normal="60" />
		</collision>
	</npc>
	<npc id="23960" level="99" type="L2Npc" name="Banshee" title="u,Queen’s Maid">
		<!-- AUTO GENERATED NPC TODO: FIX IT -->
		<race>HUMAN</race>
		<sex>FEMALE</sex>
		<stats str="40" int="21" dex="30" wit="20" con="43" men="10">
			<vitals hp="15841" hpRegen="10.5" mp="2355" mpRegen="3.6" />
			<speed>
				<walk ground="1" />
				<run ground="210" />
			</speed>
			<attack physical="1950.2231755595" magical="1331.5869440987" critical="4" attackSpeed="253" range="40" />
			<defence physical="405.85106382979" magical="297.0297029703" />
		</stats>
		<status attackable="false" />
		<skill_list>
			<skill id="4045" level="1" /> <!-- Full Magic Attack Resistance -->
		</skill_list>
		<collision>
			<radius normal="30" />
			<height normal="60" />
		</collision>
	</npc>
	<npc id="23961" level="99" type="L2Npc" name="Angel">
		<!-- AUTO GENERATED NPC TODO: FIX IT -->
		<race>HUMAN</race>
		<sex>FEMALE</sex>
		<stats str="40" int="21" dex="30" wit="20" con="43" men="10">
			<vitals hp="15841" hpRegen="10.5" mp="2355" mpRegen="3.6" />
			<speed>
				<walk ground="1" />
				<run ground="210" />
			</speed>
			<attack physical="1950.2231755595" magical="1331.5869440987" critical="4" attackSpeed="253" range="40" />
			<defence physical="405.85106382979" magical="297.0297029703" />
		</stats>
		<status attackable="false" />
		<skill_list>
			<skill id="4045" level="1" /> <!-- Full Magic Attack Resistance -->
		</skill_list>
		<collision>
			<radius normal="30" />
			<height normal="60" />
		</collision>
	</npc>
	<npc id="23962" level="99" type="L2Npc" name="Baby Golden Pig">
		<!-- AUTO GENERATED NPC TODO: FIX IT -->
		<race>HUMAN</race>
		<sex>FEMALE</sex>
		<stats str="40" int="21" dex="30" wit="20" con="43" men="10">
			<vitals hp="15841" hpRegen="10.5" mp="2355" mpRegen="3.6" />
			<speed>
				<walk ground="1" />
				<run ground="210" />
			</speed>
			<attack physical="1950.2231755595" magical="1331.5869440987" critical="4" attackSpeed="253" range="40" />
			<defence physical="405.85106382979" magical="297.0297029703" />
		</stats>
		<status attackable="false" />
		<skill_list>
			<skill id="4045" level="1" /> <!-- Full Magic Attack Resistance -->
		</skill_list>
		<collision>
			<radius normal="30" />
			<height normal="60" />
		</collision>
	</npc>
	<npc id="23963" level="99" type="L2Npc" name="Small Bard">
		<!-- AUTO GENERATED NPC TODO: FIX IT -->
		<race>HUMAN</race>
		<sex>FEMALE</sex>
		<stats str="40" int="21" dex="30" wit="20" con="43" men="10">
			<vitals hp="15841" hpRegen="10.5" mp="2355" mpRegen="3.6" />
			<speed>
				<walk ground="1" />
				<run ground="210" />
			</speed>
			<attack physical="1950.2231755595" magical="1331.5869440987" critical="4" attackSpeed="253" range="40" />
			<defence physical="405.85106382979" magical="297.0297029703" />
		</stats>
		<status attackable="false" />
		<skill_list>
			<skill id="4045" level="1" /> <!-- Full Magic Attack Resistance -->
		</skill_list>
		<collision>
			<radius normal="30" />
			<height normal="60" />
		</collision>
	</npc>
	<npc id="23964" level="99" type="L2Npc" name="Would-be Gatekeeper">
		<!-- AUTO GENERATED NPC TODO: FIX IT -->
		<race>HUMAN</race>
		<sex>FEMALE</sex>
		<stats str="40" int="21" dex="30" wit="20" con="43" men="10">
			<vitals hp="15841" hpRegen="10.5" mp="2355" mpRegen="3.6" />
			<speed>
				<walk ground="1" />
				<run ground="210" />
			</speed>
			<attack physical="1950.2231755595" magical="1331.5869440987" critical="4" attackSpeed="253" range="40" />
			<defence physical="405.85106382979" magical="297.0297029703" />
		</stats>
		<status attackable="false" />
		<skill_list>
			<skill id="4045" level="1" /> <!-- Full Magic Attack Resistance -->
		</skill_list>
		<collision>
			<radius normal="30" />
			<height normal="60" />
		</collision>
	</npc>
	<npc id="23965" level="99" type="L2Npc" name="Kat the Cat">
		<!-- AUTO GENERATED NPC TODO: FIX IT -->
		<race>HUMAN</race>
		<sex>FEMALE</sex>
		<stats str="40" int="21" dex="30" wit="20" con="43" men="10">
			<vitals hp="15841" hpRegen="10.5" mp="2355" mpRegen="3.6" />
			<speed>
				<walk ground="1" />
				<run ground="210" />
			</speed>
			<attack physical="1950.2231755595" magical="1331.5869440987" critical="4" attackSpeed="253" range="40" />
			<defence physical="405.85106382979" magical="297.0297029703" />
		</stats>
		<status attackable="false" />
		<skill_list>
			<skill id="4045" level="1" /> <!-- Full Magic Attack Resistance -->
		</skill_list>
		<collision>
			<radius normal="30" />
			<height normal="60" />
		</collision>
	</npc>
	<npc id="23966" level="99" type="L2Npc" name="Mew the Cat">
		<!-- AUTO GENERATED NPC TODO: FIX IT -->
		<race>HUMAN</race>
		<sex>FEMALE</sex>
		<stats str="40" int="21" dex="30" wit="20" con="43" men="10">
			<vitals hp="15841" hpRegen="10.5" mp="2355" mpRegen="3.6" />
			<speed>
				<walk ground="1" />
				<run ground="210" />
			</speed>
			<attack physical="1950.2231755595" magical="1331.5869440987" critical="4" attackSpeed="253" range="40" />
			<defence physical="405.85106382979" magical="297.0297029703" />
		</stats>
		<status attackable="false" />
		<skill_list>
			<skill id="4045" level="1" /> <!-- Full Magic Attack Resistance -->
		</skill_list>
		<collision>
			<radius normal="30" />
			<height normal="60" />
		</collision>
	</npc>
	<npc id="23967" level="99" type="L2Npc" name="Feline Queen">
		<!-- AUTO GENERATED NPC TODO: FIX IT -->
		<race>HUMAN</race>
		<sex>FEMALE</sex>
		<stats str="40" int="21" dex="30" wit="20" con="43" men="10">
			<vitals hp="15841" hpRegen="10.5" mp="2355" mpRegen="3.6" />
			<speed>
				<walk ground="1" />
				<run ground="210" />
			</speed>
			<attack physical="1950.2231755595" magical="1331.5869440987" critical="4" attackSpeed="253" range="40" />
			<defence physical="405.85106382979" magical="297.0297029703" />
		</stats>
		<status attackable="false" />
		<skill_list>
			<skill id="4045" level="1" /> <!-- Full Magic Attack Resistance -->
		</skill_list>
		<collision>
			<radius normal="30" />
			<height normal="60" />
		</collision>
	</npc>
	<npc id="23968" level="99" type="L2Npc" name="Roa Fan Club Human">
		<!-- AUTO GENERATED NPC TODO: FIX IT -->
		<race>HUMAN</race>
		<sex>FEMALE</sex>
		<stats str="40" int="21" dex="30" wit="20" con="43" men="10">
			<vitals hp="15841" hpRegen="10.5" mp="2355" mpRegen="3.6" />
			<speed>
				<walk ground="1" />
				<run ground="210" />
			</speed>
			<attack physical="1950.2231755595" magical="1331.5869440987" critical="4" attackSpeed="253" range="40" />
			<defence physical="405.85106382979" magical="297.0297029703" />
		</stats>
		<status attackable="false" />
		<skill_list>
			<skill id="4045" level="1" /> <!-- Full Magic Attack Resistance -->
		</skill_list>
		<collision>
			<radius normal="30" />
			<height normal="60" />
		</collision>
	</npc>
	<npc id="23969" level="99" type="L2Npc" name="Roa Fan Club Dwarf">
		<!-- AUTO GENERATED NPC TODO: FIX IT -->
		<race>HUMAN</race>
		<sex>FEMALE</sex>
		<stats str="40" int="21" dex="30" wit="20" con="43" men="10">
			<vitals hp="15841" hpRegen="10.5" mp="2355" mpRegen="3.6" />
			<speed>
				<walk ground="1" />
				<run ground="210" />
			</speed>
			<attack physical="1950.2231755595" magical="1331.5869440987" critical="4" attackSpeed="253" range="40" />
			<defence physical="405.85106382979" magical="297.0297029703" />
		</stats>
		<status attackable="false" />
		<skill_list>
			<skill id="4045" level="1" /> <!-- Full Magic Attack Resistance -->
		</skill_list>
		<collision>
			<radius normal="30" />
			<height normal="60" />
		</collision>
	</npc>
	<npc id="23970" level="99" type="L2Npc" name="u,Dandy’s Dinosaur Friend">
		<!-- AUTO GENERATED NPC TODO: FIX IT -->
		<race>HUMAN</race>
		<sex>FEMALE</sex>
		<stats str="40" int="21" dex="30" wit="20" con="43" men="10">
			<vitals hp="15841" hpRegen="10.5" mp="2355" mpRegen="3.6" />
			<speed>
				<walk ground="1" />
				<run ground="210" />
			</speed>
			<attack physical="1950.2231755595" magical="1331.5869440987" critical="4" attackSpeed="253" range="40" />
			<defence physical="405.85106382979" magical="297.0297029703" />
		</stats>
		<status attackable="false" />
		<skill_list>
			<skill id="4045" level="1" /> <!-- Full Magic Attack Resistance -->
		</skill_list>
		<collision>
			<radius normal="30" />
			<height normal="60" />
		</collision>
	</npc>
	<npc id="23971" level="99" type="L2Npc" name="Veil Master" title="Aide of the Blood Queen">
		<!-- AUTO GENERATED NPC TODO: FIX IT -->
		<race>HUMAN</race>
		<sex>FEMALE</sex>
		<stats str="40" int="21" dex="30" wit="20" con="43" men="10">
			<vitals hp="15841" hpRegen="10.5" mp="2355" mpRegen="3.6" />
			<speed>
				<walk ground="1" />
				<run ground="210" />
			</speed>
			<attack physical="1950.2231755595" magical="1331.5869440987" critical="4" attackSpeed="253" range="40" />
			<defence physical="405.85106382979" magical="297.0297029703" />
		</stats>
		<status attackable="false" />
		<skill_list>
			<skill id="4045" level="1" /> <!-- Full Magic Attack Resistance -->
		</skill_list>
		<collision>
			<radius normal="30" />
			<height normal="60" />
		</collision>
	</npc>
	<npc id="23972" level="99" type="L2Npc" name="Tanta Healer" title="u,Commander’s Medic">
		<!-- AUTO GENERATED NPC TODO: FIX IT -->
		<race>HUMAN</race>
		<sex>FEMALE</sex>
		<stats str="40" int="21" dex="30" wit="20" con="43" men="10">
			<vitals hp="15841" hpRegen="10.5" mp="2355" mpRegen="3.6" />
			<speed>
				<walk ground="1" />
				<run ground="210" />
			</speed>
			<attack physical="1950.2231755595" magical="1331.5869440987" critical="4" attackSpeed="253" range="40" />
			<defence physical="405.85106382979" magical="297.0297029703" />
		</stats>
		<status attackable="false" />
		<skill_list>
			<skill id="4045" level="1" /> <!-- Full Magic Attack Resistance -->
		</skill_list>
		<collision>
			<radius normal="30" />
			<height normal="60" />
		</collision>
	</npc>
	<npc id="23973" level="99" type="L2Npc" name="Young Poisonous Spider">
		<!-- AUTO GENERATED NPC TODO: FIX IT -->
		<race>HUMAN</race>
		<sex>FEMALE</sex>
		<stats str="40" int="21" dex="30" wit="20" con="43" men="10">
			<vitals hp="15841" hpRegen="10.5" mp="2355" mpRegen="3.6" />
			<speed>
				<walk ground="1" />
				<run ground="210" />
			</speed>
			<attack physical="1950.2231755595" magical="1331.5869440987" critical="4" attackSpeed="253" range="40" />
			<defence physical="405.85106382979" magical="297.0297029703" />
		</stats>
		<status attackable="false" />
		<skill_list>
			<skill id="4045" level="1" /> <!-- Full Magic Attack Resistance -->
		</skill_list>
		<collision>
			<radius normal="30" />
			<height normal="60" />
		</collision>
	</npc>
	<npc id="23974" level="99" type="L2Npc" name="Young Stakato">
		<!-- AUTO GENERATED NPC TODO: FIX IT -->
		<race>HUMAN</race>
		<sex>FEMALE</sex>
		<stats str="40" int="21" dex="30" wit="20" con="43" men="10">
			<vitals hp="15841" hpRegen="10.5" mp="2355" mpRegen="3.6" />
			<speed>
				<walk ground="1" />
				<run ground="210" />
			</speed>
			<attack physical="1950.2231755595" magical="1331.5869440987" critical="4" attackSpeed="253" range="40" />
			<defence physical="405.85106382979" magical="297.0297029703" />
		</stats>
		<status attackable="false" />
		<skill_list>
			<skill id="4045" level="1" /> <!-- Full Magic Attack Resistance -->
		</skill_list>
		<collision>
			<radius normal="30" />
			<height normal="60" />
		</collision>
	</npc>
	<npc id="23975" level="99" type="L2Npc" name="Banshee" title="u,Queen’s Maid">
		<!-- AUTO GENERATED NPC TODO: FIX IT -->
		<race>HUMAN</race>
		<sex>FEMALE</sex>
		<stats str="40" int="21" dex="30" wit="20" con="43" men="10">
			<vitals hp="15841" hpRegen="10.5" mp="2355" mpRegen="3.6" />
			<speed>
				<walk ground="1" />
				<run ground="210" />
			</speed>
			<attack physical="1950.2231755595" magical="1331.5869440987" critical="4" attackSpeed="253" range="40" />
			<defence physical="405.85106382979" magical="297.0297029703" />
		</stats>
		<status attackable="false" />
		<skill_list>
			<skill id="4045" level="1" /> <!-- Full Magic Attack Resistance -->
		</skill_list>
		<collision>
			<radius normal="30" />
			<height normal="60" />
		</collision>
	</npc>
	<npc id="23976" level="99" type="L2Npc" name="Angel">
		<!-- AUTO GENERATED NPC TODO: FIX IT -->
		<race>HUMAN</race>
		<sex>FEMALE</sex>
		<stats str="40" int="21" dex="30" wit="20" con="43" men="10">
			<vitals hp="15841" hpRegen="10.5" mp="2355" mpRegen="3.6" />
			<speed>
				<walk ground="1" />
				<run ground="210" />
			</speed>
			<attack physical="1950.2231755595" magical="1331.5869440987" critical="4" attackSpeed="253" range="40" />
			<defence physical="405.85106382979" magical="297.0297029703" />
		</stats>
		<status attackable="false" />
		<skill_list>
			<skill id="4045" level="1" /> <!-- Full Magic Attack Resistance -->
		</skill_list>
		<collision>
			<radius normal="30" />
			<height normal="60" />
		</collision>
	</npc>
	<npc id="23977" level="99" type="L2Npc" name="Baby Golden Pig">
		<!-- AUTO GENERATED NPC TODO: FIX IT -->
		<race>HUMAN</race>
		<sex>FEMALE</sex>
		<stats str="40" int="21" dex="30" wit="20" con="43" men="10">
			<vitals hp="15841" hpRegen="10.5" mp="2355" mpRegen="3.6" />
			<speed>
				<walk ground="1" />
				<run ground="210" />
			</speed>
			<attack physical="1950.2231755595" magical="1331.5869440987" critical="4" attackSpeed="253" range="40" />
			<defence physical="405.85106382979" magical="297.0297029703" />
		</stats>
		<status attackable="false" />
		<skill_list>
			<skill id="4045" level="1" /> <!-- Full Magic Attack Resistance -->
		</skill_list>
		<collision>
			<radius normal="30" />
			<height normal="60" />
		</collision>
	</npc>
	<npc id="23978" level="99" type="L2Npc" name="Small Bard">
		<!-- AUTO GENERATED NPC TODO: FIX IT -->
		<race>HUMAN</race>
		<sex>FEMALE</sex>
		<stats str="40" int="21" dex="30" wit="20" con="43" men="10">
			<vitals hp="15841" hpRegen="10.5" mp="2355" mpRegen="3.6" />
			<speed>
				<walk ground="1" />
				<run ground="210" />
			</speed>
			<attack physical="1950.2231755595" magical="1331.5869440987" critical="4" attackSpeed="253" range="40" />
			<defence physical="405.85106382979" magical="297.0297029703" />
		</stats>
		<status attackable="false" />
		<skill_list>
			<skill id="4045" level="1" /> <!-- Full Magic Attack Resistance -->
		</skill_list>
		<collision>
			<radius normal="30" />
			<height normal="60" />
		</collision>
	</npc>
	<npc id="23979" level="99" type="L2Npc" name="Would-be Gatekeeper">
		<!-- AUTO GENERATED NPC TODO: FIX IT -->
		<race>HUMAN</race>
		<sex>FEMALE</sex>
		<stats str="40" int="21" dex="30" wit="20" con="43" men="10">
			<vitals hp="15841" hpRegen="10.5" mp="2355" mpRegen="3.6" />
			<speed>
				<walk ground="1" />
				<run ground="210" />
			</speed>
			<attack physical="1950.2231755595" magical="1331.5869440987" critical="4" attackSpeed="253" range="40" />
			<defence physical="405.85106382979" magical="297.0297029703" />
		</stats>
		<status attackable="false" />
		<skill_list>
			<skill id="4045" level="1" /> <!-- Full Magic Attack Resistance -->
		</skill_list>
		<collision>
			<radius normal="30" />
			<height normal="60" />
		</collision>
	</npc>
	<npc id="23980" level="99" type="L2Npc" name="Kat the Cat">
		<!-- AUTO GENERATED NPC TODO: FIX IT -->
		<race>HUMAN</race>
		<sex>FEMALE</sex>
		<stats str="40" int="21" dex="30" wit="20" con="43" men="10">
			<vitals hp="15841" hpRegen="10.5" mp="2355" mpRegen="3.6" />
			<speed>
				<walk ground="1" />
				<run ground="210" />
			</speed>
			<attack physical="1950.2231755595" magical="1331.5869440987" critical="4" attackSpeed="253" range="40" />
			<defence physical="405.85106382979" magical="297.0297029703" />
		</stats>
		<status attackable="false" />
		<skill_list>
			<skill id="4045" level="1" /> <!-- Full Magic Attack Resistance -->
		</skill_list>
		<collision>
			<radius normal="30" />
			<height normal="60" />
		</collision>
	</npc>
	<npc id="23981" level="99" type="L2Npc" name="Mew the Cat">
		<!-- AUTO GENERATED NPC TODO: FIX IT -->
		<race>HUMAN</race>
		<sex>FEMALE</sex>
		<stats str="40" int="21" dex="30" wit="20" con="43" men="10">
			<vitals hp="15841" hpRegen="10.5" mp="2355" mpRegen="3.6" />
			<speed>
				<walk ground="1" />
				<run ground="210" />
			</speed>
			<attack physical="1950.2231755595" magical="1331.5869440987" critical="4" attackSpeed="253" range="40" />
			<defence physical="405.85106382979" magical="297.0297029703" />
		</stats>
		<status attackable="false" />
		<skill_list>
			<skill id="4045" level="1" /> <!-- Full Magic Attack Resistance -->
		</skill_list>
		<collision>
			<radius normal="30" />
			<height normal="60" />
		</collision>
	</npc>
	<npc id="23982" level="99" type="L2Npc" name="Feline Queen">
		<!-- AUTO GENERATED NPC TODO: FIX IT -->
		<race>HUMAN</race>
		<sex>FEMALE</sex>
		<stats str="40" int="21" dex="30" wit="20" con="43" men="10">
			<vitals hp="15841" hpRegen="10.5" mp="2355" mpRegen="3.6" />
			<speed>
				<walk ground="1" />
				<run ground="210" />
			</speed>
			<attack physical="1950.2231755595" magical="1331.5869440987" critical="4" attackSpeed="253" range="40" />
			<defence physical="405.85106382979" magical="297.0297029703" />
		</stats>
		<status attackable="false" />
		<skill_list>
			<skill id="4045" level="1" /> <!-- Full Magic Attack Resistance -->
		</skill_list>
		<collision>
			<radius normal="30" />
			<height normal="60" />
		</collision>
	</npc>
	<npc id="23983" level="99" type="L2Npc" name="Roa Fan Club Human">
		<!-- AUTO GENERATED NPC TODO: FIX IT -->
		<race>HUMAN</race>
		<sex>FEMALE</sex>
		<stats str="40" int="21" dex="30" wit="20" con="43" men="10">
			<vitals hp="15841" hpRegen="10.5" mp="2355" mpRegen="3.6" />
			<speed>
				<walk ground="1" />
				<run ground="210" />
			</speed>
			<attack physical="1950.2231755595" magical="1331.5869440987" critical="4" attackSpeed="253" range="40" />
			<defence physical="405.85106382979" magical="297.0297029703" />
		</stats>
		<status attackable="false" />
		<skill_list>
			<skill id="4045" level="1" /> <!-- Full Magic Attack Resistance -->
		</skill_list>
		<collision>
			<radius normal="30" />
			<height normal="60" />
		</collision>
	</npc>
	<npc id="23984" level="99" type="L2Npc" name="Roa Fan Club Dwarf">
		<!-- AUTO GENERATED NPC TODO: FIX IT -->
		<race>HUMAN</race>
		<sex>FEMALE</sex>
		<stats str="40" int="21" dex="30" wit="20" con="43" men="10">
			<vitals hp="15841" hpRegen="10.5" mp="2355" mpRegen="3.6" />
			<speed>
				<walk ground="1" />
				<run ground="210" />
			</speed>
			<attack physical="1950.2231755595" magical="1331.5869440987" critical="4" attackSpeed="253" range="40" />
			<defence physical="405.85106382979" magical="297.0297029703" />
		</stats>
		<status attackable="false" />
		<skill_list>
			<skill id="4045" level="1" /> <!-- Full Magic Attack Resistance -->
		</skill_list>
		<collision>
			<radius normal="30" />
			<height normal="60" />
		</collision>
	</npc>
	<npc id="23985" level="99" type="L2Npc" name="u,Dandy’s Dinosaur Friend">
		<!-- AUTO GENERATED NPC TODO: FIX IT -->
		<race>HUMAN</race>
		<sex>FEMALE</sex>
		<stats str="40" int="21" dex="30" wit="20" con="43" men="10">
			<vitals hp="15841" hpRegen="10.5" mp="2355" mpRegen="3.6" />
			<speed>
				<walk ground="1" />
				<run ground="210" />
			</speed>
			<attack physical="1950.2231755595" magical="1331.5869440987" critical="4" attackSpeed="253" range="40" />
			<defence physical="405.85106382979" magical="297.0297029703" />
		</stats>
		<status attackable="false" />
		<skill_list>
			<skill id="4045" level="1" /> <!-- Full Magic Attack Resistance -->
		</skill_list>
		<collision>
			<radius normal="30" />
			<height normal="60" />
		</collision>
	</npc>
	<npc id="23986" level="99" type="L2Npc" name="Leona Blackbird" title="u,Dragon’s Advocate">
		<!-- AUTO GENERATED NPC TODO: FIX IT -->
		<race>HUMAN</race>
		<sex>FEMALE</sex>
		<stats str="40" int="21" dex="30" wit="20" con="43" men="10">
			<vitals hp="15841" hpRegen="10.5" mp="2355" mpRegen="3.6" />
			<speed>
				<walk ground="1" />
				<run ground="210" />
			</speed>
			<attack physical="1950.2231755595" magical="1331.5869440987" critical="4" attackSpeed="253" range="40" />
			<defence physical="405.85106382979" magical="297.0297029703" />
		</stats>
		<status attackable="false" />
		<skill_list>
			<skill id="4045" level="1" /> <!-- Full Magic Attack Resistance -->
		</skill_list>
		<collision>
			<radius normal="30" />
			<height normal="60" />
		</collision>
	</npc>
	<npc id="23987" level="99" type="L2Npc" name="Kain Van Halter" title="Prince of the Second Dimension">
		<!-- AUTO GENERATED NPC TODO: FIX IT -->
		<race>HUMAN</race>
		<sex>FEMALE</sex>
		<stats str="40" int="21" dex="30" wit="20" con="43" men="10">
			<vitals hp="15841" hpRegen="10.5" mp="2355" mpRegen="3.6" />
			<speed>
				<walk ground="1" />
				<run ground="210" />
			</speed>
			<attack physical="1950.2231755595" magical="1331.5869440987" critical="4" attackSpeed="253" range="40" />
			<defence physical="405.85106382979" magical="297.0297029703" />
		</stats>
		<status attackable="false" />
		<skill_list>
			<skill id="4045" level="1" /> <!-- Full Magic Attack Resistance -->
		</skill_list>
		<collision>
			<radius normal="30" />
			<height normal="60" />
		</collision>
	</npc>
	<npc id="23988" level="99" type="L2Npc" name="Queen Ant" title="Successor in the Ant Nest">
		<!-- AUTO GENERATED NPC TODO: FIX IT -->
		<race>HUMAN</race>
		<sex>FEMALE</sex>
		<stats str="40" int="21" dex="30" wit="20" con="43" men="10">
			<vitals hp="15841" hpRegen="10.5" mp="2355" mpRegen="3.6" />
			<speed>
				<walk ground="1" />
				<run ground="210" />
			</speed>
			<attack physical="1950.2231755595" magical="1331.5869440987" critical="4" attackSpeed="253" range="40" />
			<defence physical="405.85106382979" magical="297.0297029703" />
		</stats>
		<status attackable="false" />
		<skill_list>
			<skill id="4045" level="1" /> <!-- Full Magic Attack Resistance -->
		</skill_list>
		<collision>
			<radius normal="30" />
			<height normal="60" />
		</collision>
	</npc>
	<npc id="23989" level="99" type="L2Npc" name="Escort Ant">
		<!-- AUTO GENERATED NPC TODO: FIX IT -->
		<race>HUMAN</race>
		<sex>FEMALE</sex>
		<stats str="40" int="21" dex="30" wit="20" con="43" men="10">
			<vitals hp="15841" hpRegen="10.5" mp="2355" mpRegen="3.6" />
			<speed>
				<walk ground="1" />
				<run ground="210" />
			</speed>
			<attack physical="1950.2231755595" magical="1331.5869440987" critical="4" attackSpeed="253" range="40" />
			<defence physical="405.85106382979" magical="297.0297029703" />
		</stats>
		<status attackable="false" />
		<skill_list>
			<skill id="4045" level="1" /> <!-- Full Magic Attack Resistance -->
		</skill_list>
		<collision>
			<radius normal="30" />
			<height normal="60" />
		</collision>
	</npc>
	<npc id="23990" level="99" type="L2Npc" name="Royal Guard Ant">
		<!-- AUTO GENERATED NPC TODO: FIX IT -->
		<race>HUMAN</race>
		<sex>FEMALE</sex>
		<stats str="40" int="21" dex="30" wit="20" con="43" men="10">
			<vitals hp="15841" hpRegen="10.5" mp="2355" mpRegen="3.6" />
			<speed>
				<walk ground="1" />
				<run ground="210" />
			</speed>
			<attack physical="1950.2231755595" magical="1331.5869440987" critical="4" attackSpeed="253" range="40" />
			<defence physical="405.85106382979" magical="297.0297029703" />
		</stats>
		<status attackable="false" />
		<skill_list>
			<skill id="4045" level="1" /> <!-- Full Magic Attack Resistance -->
		</skill_list>
		<collision>
			<radius normal="30" />
			<height normal="60" />
		</collision>
	</npc>
	<npc id="23991" level="99" type="L2Npc" name="Urfen" title="Orfen Kin">
		<!-- AUTO GENERATED NPC TODO: FIX IT -->
		<race>HUMAN</race>
		<sex>FEMALE</sex>
		<stats str="40" int="21" dex="30" wit="20" con="43" men="10">
			<vitals hp="15841" hpRegen="10.5" mp="2355" mpRegen="3.6" />
			<speed>
				<walk ground="1" />
				<run ground="210" />
			</speed>
			<attack physical="1950.2231755595" magical="1331.5869440987" critical="4" attackSpeed="253" range="40" />
			<defence physical="405.85106382979" magical="297.0297029703" />
		</stats>
		<status attackable="false" />
		<skill_list>
			<skill id="4045" level="1" /> <!-- Full Magic Attack Resistance -->
		</skill_list>
		<collision>
			<radius normal="30" />
			<height normal="60" />
		</collision>
	</npc>
	<npc id="23992" level="99" type="L2Npc" name="Laikel">
		<!-- AUTO GENERATED NPC TODO: FIX IT -->
		<race>HUMAN</race>
		<sex>FEMALE</sex>
		<stats str="40" int="21" dex="30" wit="20" con="43" men="10">
			<vitals hp="15841" hpRegen="10.5" mp="2355" mpRegen="3.6" />
			<speed>
				<walk ground="1" />
				<run ground="210" />
			</speed>
			<attack physical="1950.2231755595" magical="1331.5869440987" critical="4" attackSpeed="253" range="40" />
			<defence physical="405.85106382979" magical="297.0297029703" />
		</stats>
		<status attackable="false" />
		<skill_list>
			<skill id="4045" level="1" /> <!-- Full Magic Attack Resistance -->
		</skill_list>
		<collision>
			<radius normal="30" />
			<height normal="60" />
		</collision>
	</npc>
	<npc id="23993" level="99" type="L2Npc" name="Riba">
		<!-- AUTO GENERATED NPC TODO: FIX IT -->
		<race>HUMAN</race>
		<sex>FEMALE</sex>
		<stats str="40" int="21" dex="30" wit="20" con="43" men="10">
			<vitals hp="15841" hpRegen="10.5" mp="2355" mpRegen="3.6" />
			<speed>
				<walk ground="1" />
				<run ground="210" />
			</speed>
			<attack physical="1950.2231755595" magical="1331.5869440987" critical="4" attackSpeed="253" range="40" />
			<defence physical="405.85106382979" magical="297.0297029703" />
		</stats>
		<status attackable="false" />
		<skill_list>
			<skill id="4045" level="1" /> <!-- Full Magic Attack Resistance -->
		</skill_list>
		<collision>
			<radius normal="30" />
			<height normal="60" />
		</collision>
	</npc>
	<npc id="23994" level="99" type="L2Npc" name="Zaken" title="Unworldly Pirate King">
		<!-- AUTO GENERATED NPC TODO: FIX IT -->
		<race>HUMAN</race>
		<sex>FEMALE</sex>
		<stats str="40" int="21" dex="30" wit="20" con="43" men="10">
			<vitals hp="15841" hpRegen="10.5" mp="2355" mpRegen="3.6" />
			<speed>
				<walk ground="1" />
				<run ground="210" />
			</speed>
			<attack physical="1950.2231755595" magical="1331.5869440987" critical="4" attackSpeed="253" range="40" />
			<defence physical="405.85106382979" magical="297.0297029703" />
		</stats>
		<status attackable="false" />
		<skill_list>
			<skill id="4045" level="1" /> <!-- Full Magic Attack Resistance -->
		</skill_list>
		<collision>
			<radius normal="30" />
			<height normal="60" />
		</collision>
	</npc>
	<npc id="23995" level="99" type="L2Npc" name="Zaken" title="Unworldly Pirate King">
		<!-- AUTO GENERATED NPC TODO: FIX IT -->
		<race>HUMAN</race>
		<sex>FEMALE</sex>
		<stats str="40" int="21" dex="30" wit="20" con="43" men="10">
			<vitals hp="15841" hpRegen="10.5" mp="2355" mpRegen="3.6" />
			<speed>
				<walk ground="1" />
				<run ground="210" />
			</speed>
			<attack physical="1950.2231755595" magical="1331.5869440987" critical="4" attackSpeed="253" range="40" />
			<defence physical="405.85106382979" magical="297.0297029703" />
		</stats>
		<status attackable="false" />
		<skill_list>
			<skill id="4045" level="1" /> <!-- Full Magic Attack Resistance -->
		</skill_list>
		<collision>
			<radius normal="30" />
			<height normal="60" />
		</collision>
	</npc>
	<npc id="23996" level="99" type="L2Npc" name="Pirate Zombie Captain">
		<!-- AUTO GENERATED NPC TODO: FIX IT -->
		<race>HUMAN</race>
		<sex>FEMALE</sex>
		<stats str="40" int="21" dex="30" wit="20" con="43" men="10">
			<vitals hp="15841" hpRegen="10.5" mp="2355" mpRegen="3.6" />
			<speed>
				<walk ground="1" />
				<run ground="210" />
			</speed>
			<attack physical="1950.2231755595" magical="1331.5869440987" critical="4" attackSpeed="253" range="40" />
			<defence physical="405.85106382979" magical="297.0297029703" />
		</stats>
		<status attackable="false" />
		<skill_list>
			<skill id="4045" level="1" /> <!-- Full Magic Attack Resistance -->
		</skill_list>
		<collision>
			<radius normal="30" />
			<height normal="60" />
		</collision>
	</npc>
	<npc id="23997" level="99" type="L2Npc" name="Pirate Zombie">
		<!-- AUTO GENERATED NPC TODO: FIX IT -->
		<race>HUMAN</race>
		<sex>FEMALE</sex>
		<stats str="40" int="21" dex="30" wit="20" con="43" men="10">
			<vitals hp="15841" hpRegen="10.5" mp="2355" mpRegen="3.6" />
			<speed>
				<walk ground="1" />
				<run ground="210" />
			</speed>
			<attack physical="1950.2231755595" magical="1331.5869440987" critical="4" attackSpeed="253" range="40" />
			<defence physical="405.85106382979" magical="297.0297029703" />
		</stats>
		<status attackable="false" />
		<skill_list>
			<skill id="4045" level="1" /> <!-- Full Magic Attack Resistance -->
		</skill_list>
		<collision>
			<radius normal="30" />
			<height normal="60" />
		</collision>
	</npc>
	<npc id="23998" level="99" type="L2Npc" name="Saium" title="Relative of the Emperor">
		<!-- AUTO GENERATED NPC TODO: FIX IT -->
		<race>HUMAN</race>
		<sex>FEMALE</sex>
		<stats str="40" int="21" dex="30" wit="20" con="43" men="10">
			<vitals hp="15841" hpRegen="10.5" mp="2355" mpRegen="3.6" />
			<speed>
				<walk ground="1" />
				<run ground="210" />
			</speed>
			<attack physical="1950.2231755595" magical="1331.5869440987" critical="4" attackSpeed="253" range="40" />
			<defence physical="405.85106382979" magical="297.0297029703" />
		</stats>
		<status attackable="false" />
		<skill_list>
			<skill id="4045" level="1" /> <!-- Full Magic Attack Resistance -->
		</skill_list>
		<collision>
			<radius normal="30" />
			<height normal="60" />
		</collision>
	</npc>
	<npc id="23999" level="99" type="L2Npc" name="Traitor Angel">
		<!-- AUTO GENERATED NPC TODO: FIX IT -->
		<race>HUMAN</race>
		<sex>FEMALE</sex>
		<stats str="40" int="21" dex="30" wit="20" con="43" men="10">
			<vitals hp="15841" hpRegen="10.5" mp="2355" mpRegen="3.6" />
			<speed>
				<walk ground="1" />
				<run ground="210" />
			</speed>
			<attack physical="1950.2231755595" magical="1331.5869440987" critical="4" attackSpeed="253" range="40" />
			<defence physical="405.85106382979" magical="297.0297029703" />
		</stats>
		<status attackable="false" />
		<skill_list>
			<skill id="4045" level="1" /> <!-- Full Magic Attack Resistance -->
		</skill_list>
		<collision>
			<radius normal="30" />
			<height normal="60" />
		</collision>
	</npc>
</list>